Workbook

Sheet Dados
A1: DATA_REL | B1: TP_DESP | C1: CNPJ_CPF | D1: NOME | E1: REFERÊNCIA | F1: NF | G1: VR_UNIT | H1: DIAS | I1: VALOR | J1: DT_VENCTO | K1: CATEGORIA | L1: DADOS_BANCARIOS | M1: OBSERVAÇÃO

Sheet RESUMO
G1: Rua Zodiaco, 87 Sala 07 – Santa Lúcia - Belo Horizonte - MG (31) 3654-6616 / (31) 99974-1241 / (31) 98711-1139 rvr.engenharia@gmail.com / vinicius.rinaldi26@gmail.com
A3: [NOME] | K3: Data Inicial:
A4: [ENDEREÇO] | K4: % Adm Obra:
A6: RESUMO DAS DESPESAS
C7: 1 | D7: 2 | E7: 3 | F7: 4 | G7: 5 | H7: 6
A8: DATA | B8: Nº REL. | C8: 1) DESPESAS COM COLABORADORES | D8: 2) TRANSF. PROGR. - MATERIAIS, LOCAÇÕES E PREST. SERVIÇOS | E8: 3) MATERIAIS, PREST DE SERVIÇOS, IMPOSTOS E OUTROS | F8: 4) RESSARCIMENTOS E RESTITUIÇÕES | G8: 5) DESPESAS PAGAS PELO CLIENTE | H8: 6) PAGAMENTOS CAIXA DE OBRA | I8: SUBTOTAL | J8: 7) ADM. OBRA | K8: TOTAL | L8: ACUMULADO
A9: =Dados!$A$2 -> 0 | B9: 1 | C9: =SUMIFS(Dados!$I$1:$I$1993,Dados!$B$1:$B$1993,C$7,Dados!$A$1:$A$1993,$A9) -> 0 | D9: =SUMIFS(Dados!$I$1:$I$1993,Dados!$B$1:$B$1993,D$7,Dados!$A$1:$A$1993,$A9) -> 0 | E9: =SUMIFS(Dados!$I$1:$I$1993,Dados!$B$1:$B$1993,E$7,Dados!$A$1:$A$1993,$A9) -> 0 | F9: =SUMIFS(Dados!$I$1:$I$1993,Dados!$B$1:$B$1993,F$7,Dados!$A$1:$A$1993,$A9) -> 0 | G9: =SUMIFS(Dados!$I$1:$I$1993,Dados!$B$1:$B$1993,G$7,Dados!$A$1:$A$1993,$A9) -> 0 | H9: =SUMIFS(Dados!$I$1:$I$1993,Dados!$B$1:$B$1993,H$7,Dados!$A$1:$A$1993,$A9) -> 0 | I9: =SUM(C9:H9) -> 0 | J9: =ROUND(I9*$L$4,2) -> 0 | K9: =SUM(I9:J9) -> 0 | L9: =K9 -> 0
A10: =IF(DAY(A9)=20,DATE(YEAR(A9),MONTH(A9)+1,5),DATE(YEAR(A9),MONTH(A9),20)) -> 20 | B10: =B9+1 -> 2 | C10: =SUMIFS(Dados!$I$1:$I$1993,Dados!$B$1:$B$1993,C$7,Dados!$A$1:$A$1993,$A10) -> 0 | D10: =SUMIFS(Dados!$I$1:$I$1993,Dados!$B$1:$B$1993,D$7,Dados!$A$1:$A$1993,$A10) -> 0 | E10: =SUMIFS(Dados!$I$1:$I$1993,Dados!$B$1:$B$1993,E$7,Dados!$A$1:$A$1993,$A10) -> 0 | F10: =SUMIFS(Dados!$I$1:$I$1993,Dados!$B$1:$B$1993,F$7,Dados!$A$1:$A$1993,$A10) -> 0 | G10: =SUMIFS(Dados!$I$1:$I$1993,Dados!$B$1:$B$1993,G$7,Dados!$A$1:$A$1993,$A10) -> 0 | H10: =SUMIFS(Dados!$I$1:$I$1993,Dados!$B$1:$B$1993,H$7,Dados!$A$1:$A$1993,$A10) -> 0 | I10: =SUM(C10:H10) -> 0 | J10: =ROUND(I10*$L$4,2) -> 0 | K10: =SUM(I10:J10) -> 0 | L10: =K10+L9 -> 0
A11: =IF(DAY(A10)=20,DATE(YEAR(A10),MONTH(A10)+1,5),DATE(YEAR(A10),MONTH(A10),20)) -> 36 | B11: =B10+1 -> 3 | C11: =SUMIFS(Dados!$I$1:$I$1993,Dados!$B$1:$B$1993,C$7,Dados!$A$1:$A$1993,$A11) -> 0 | D11: =SUMIFS(Dados!$I$1:$I$1993,Dados!$B$1:$B$1993,D$7,Dados!$A$1:$A$1993,$A11) -> 0 | E11: =SUMIFS(Dados!$I$1:$I$1993,Dados!$B$1:$B$1993,E$7,Dados!$A$1:$A$1993,$A11) -> 0 | F11: =SUMIFS(Dados!$I$1:$I$1993,Dados!$B$1:$B$1993,F$7,Dados!$A$1:$A$1993,$A11) -> 0 | G11: =SUMIFS(Dados!$I$1:$I$1993,Dados!$B$1:$B$1993,G$7,Dados!$A$1:$A$1993,$A11) -> 0 | H11: =SUMIFS(Dados!$I$1:$I$1993,Dados!$B$1:$B$1993,H$7,Dados!$A$1:$A$1993,$A11) -> 0 | I11: =SUM(C11:H11) -> 0 | J11: =ROUND(I11*$L$4,2) -> 0 | K11: =SUM(I11:J11) -> 0 | L11: =K11+L10 -> 0
A12: =IF(DAY(A11)=20,DATE(YEAR(A11),MONTH(A11)+1,5),DATE(YEAR(A11),MONTH(A11),20)) -> 51 | B12: =B11+1 -> 4 | C12: =SUMIFS(Dados!$I$1:$I$1993,Dados!$B$1:$B$1993,C$7,Dados!$A$1:$A$1993,$A12) -> 0 | D12: =SUMIFS(Dados!$I$1:$I$1993,Dados!$B$1:$B$1993,D$7,Dados!$A$1:$A$1993,$A12) -> 0 | E12: =SUMIFS(Dados!$I$1:$I$1993,Dados!$B$1:$B$1993,E$7,Dados!$A$1:$A$1993,$A12) -> 0 | F12: =SUMIFS(Dados!$I$1:$I$1993,Dados!$B$1:$B$1993,F$7,Dados!$A$1:$A$1993,$A12) -> 0 | G12: =SUMIFS(Dados!$I$1:$I$1993,Dados!$B$1:$B$1993,G$7,Dados!$A$1:$A$1993,$A12) -> 0 | H12: =SUMIFS(Dados!$I$1:$I$1993,Dados!$B$1:$B$1993,H$7,Dados!$A$1:$A$1993,$A12) -> 0 | I12: =SUM(C12:H12) -> 0 | J12: =ROUND(I12*$L$4,2) -> 0 | K12: =SUM(I12:J12) -> 0 | L12: =K12+L11 -> 0
A13: =IF(DAY(A12)=20,DATE(YEAR(A12),MONTH(A12)+1,5),DATE(YEAR(A12),MONTH(A12),20)) -> 65 | B13: =B12+1 -> 5 | C13: =SUMIFS(Dados!$I$1:$I$1993,Dados!$B$1:$B$1993,C$7,Dados!$A$1:$A$1993,$A13) -> 0 | D13: =SUMIFS(Dados!$I$1:$I$1993,Dados!$B$1:$B$1993,D$7,Dados!$A$1:$A$1993,$A13) -> 0 | E13: =SUMIFS(Dados!$I$1:$I$1993,Dados!$B$1:$B$1993,E$7,Dados!$A$1:$A$1993,$A13) -> 0 | F13: =SUMIFS(Dados!$I$1:$I$1993,Dados!$B$1:$B$1993,F$7,Dados!$A$1:$A$1993,$A13) -> 0 | G13: =SUMIFS(Dados!$I$1:$I$1993,Dados!$B$1:$B$1993,G$7,Dados!$A$1:$A$1993,$A13) -> 0 | H13: =SUMIFS(Dados!$I$1:$I$1993,Dados!$B$1:$B$1993,H$7,Dados!$A$1:$A$1993,$A13) -> 0 | I13: =SUM(C13:H13) -> 0 | J13: =ROUND(I13*$L$4,2) -> 0 | K13: =SUM(I13:J13) -> 0 | L13: =K13+L12 -> 0
A14: =IF(DAY(A13)=20,DATE(YEAR(A13),MONTH(A13)+1,5),DATE(YEAR(A13),MONTH(A13),20)) -> 80 | B14: =B13+1 -> 6 | C14: =SUMIFS(Dados!$I$1:$I$1993,Dados!$B$1:$B$1993,C$7,Dados!$A$1:$A$1993,$A14) -> 0 | D14: =SUMIFS(Dados!$I$1:$I$1993,Dados!$B$1:$B$1993,D$7,Dados!$A$1:$A$1993,$A14) -> 0 | E14: =SUMIFS(Dados!$I$1:$I$1993,Dados!$B$1:$B$1993,E$7,Dados!$A$1:$A$1993,$A14) -> 0 | F14: =SUMIFS(Dados!$I$1:$I$1993,Dados!$B$1:$B$1993,F$7,Dados!$A$1:$A$1993,$A14) -> 0 | G14: =SUMIFS(Dados!$I$1:$I$1993,Dados!$B$1:$B$1993,G$7,Dados!$A$1:$A$1993,$A14) -> 0 | H14: =SUMIFS(Dados!$I$1:$I$1993,Dados!$B$1:$B$1993,H$7,Dados!$A$1:$A$1993,$A14) -> 0 | I14: =SUM(C14:H14) -> 0 | J14: =ROUND(I14*$L$4,2) -> 0 | K14: =SUM(I14:J14) -> 0 | L14: =K14+L13 -> 0
A15: =IF(DAY(A14)=20,DATE(YEAR(A14),MONTH(A14)+1,5),DATE(YEAR(A14),MONTH(A14),20)) -> 96 | B15: =B14+1 -> 7 | C15: =SUMIFS(Dados!$I$1:$I$1993,Dados!$B$1:$B$1993,C$7,Dados!$A$1:$A$1993,$A15) -> 0 | D15: =SUMIFS(Dados!$I$1:$I$1993,Dados!$B$1:$B$1993,D$7,Dados!$A$1:$A$1993,$A15) -> 0 | E15: =SUMIFS(Dados!$I$1:$I$1993,Dados!$B$1:$B$1993,E$7,Dados!$A$1:$A$1993,$A15) -> 0 | F15: =SUMIFS(Dados!$I$1:$I$1993,Dados!$B$1:$B$1993,F$7,Dados!$A$1:$A$1993,$A15) -> 0 | G15: =SUMIFS(Dados!$I$1:$I$1993,Dados!$B$1:$B$1993,G$7,Dados!$A$1:$A$1993,$A15) -> 0 | H15: =SUMIFS(Dados!$I$1:$I$1993,Dados!$B$1:$B$1993,H$7,Dados!$A$1:$A$1993,$A15) -> 0 | I15: =SUM(C15:H15) -> 0 | J15: =ROUND(I15*$L$4,2) -> 0 | K15: =SUM(I15:J15) -> 0 | L15: =K15+L14 -> 0
A16: =IF(DAY(A15)=20,DATE(YEAR(A15),MONTH(A15)+1,5),DATE(YEAR(A15),MONTH(A15),20)) -> 111 | B16: =B15+1 -> 8 | C16: =SUMIFS(Dados!$I$1:$I$1993,Dados!$B$1:$B$1993,C$7,Dados!$A$1:$A$1993,$A16) -> 0 | D16: =SUMIFS(Dados!$I$1:$I$1993,Dados!$B$1:$B$1993,D$7,Dados!$A$1:$A$1993,$A16) -> 0 | E16: =SUMIFS(Dados!$I$1:$I$1993,Dados!$B$1:$B$1993,E$7,Dados!$A$1:$A$1993,$A16) -> 0 | F16: =SUMIFS(Dados!$I$1:$I$1993,Dados!$B$1:$B$1993,F$7,Dados!$A$1:$A$1993,$A16) -> 0 | G16: =SUMIFS(Dados!$I$1:$I$1993,Dados!$B$1:$B$1993,G$7,Dados!$A$1:$A$1993,$A16) -> 0 | H16: =SUMIFS(Dados!$I$1:$I$1993,Dados!$B$1:$B$1993,H$7,Dados!$A$1:$A$1993,$A16) -> 0 | I16: =SUM(C16:H16) -> 0 | J16: =ROUND(I16*$L$4,2) -> 0 | K16: =SUM(I16:J16) -> 0 | L16: =K16+L15 -> 0
A17: =IF(DAY(A16)=20,DATE(YEAR(A16),MONTH(A16)+1,5),DATE(YEAR(A16),MONTH(A16),20)) -> 126 | B17: =B16+1 -> 9 | C17: =SUMIFS(Dados!$I$1:$I$1993,Dados!$B$1:$B$1993,C$7,Dados!$A$1:$A$1993,$A17) -> 0 | D17: =SUMIFS(Dados!$I$1:$I$1993,Dados!$B$1:$B$1993,D$7,Dados!$A$1:$A$1993,$A17) -> 0 | E17: =SUMIFS(Dados!$I$1:$I$1993,Dados!$B$1:$B$1993,E$7,Dados!$A$1:$A$1993,$A17) -> 0 | F17: =SUMIFS(Dados!$I$1:$I$1993,Dados!$B$1:$B$1993,F$7,Dados!$A$1:$A$1993,$A17) -> 0 | G17: =SUMIFS(Dados!$I$1:$I$1993,Dados!$B$1:$B$1993,G$7,Dados!$A$1:$A$1993,$A17) -> 0 | H17: =SUMIFS(Dados!$I$1:$I$1993,Dados!$B$1:$B$1993,H$7,Dados!$A$1:$A$1993,$A17) -> 0 | I17: =SUM(C17:H17) -> 0 | J17: =ROUND(I17*$L$4,2) -> 0 | K17: =SUM(I17:J17) -> 0 | L17: =K17+L16 -> 0
A18: =IF(DAY(A17)=20,DATE(YEAR(A17),MONTH(A17)+1,5),DATE(YEAR(A17),MONTH(A17),20)) -> 141 | B18: =B17+1 -> 10 | C18: =SUMIFS(Dados!$I$1:$I$1993,Dados!$B$1:$B$1993,C$7,Dados!$A$1:$A$1993,$A18) -> 0 | D18: =SUMIFS(Dados!$I$1:$I$1993,Dados!$B$1:$B$1993,D$7,Dados!$A$1:$A$1993,$A18) -> 0 | E18: =SUMIFS(Dados!$I$1:$I$1993,Dados!$B$1:$B$1993,E$7,Dados!$A$1:$A$1993,$A18) -> 0 | F18: =SUMIFS(Dados!$I$1:$I$1993,Dados!$B$1:$B$1993,F$7,Dados!$A$1:$A$1993,$A18) -> 0 | G18: =SUMIFS(Dados!$I$1:$I$1993,Dados!$B$1:$B$1993,G$7,Dados!$A$1:$A$1993,$A18) -> 0 | H18: =SUMIFS(Dados!$I$1:$I$1993,Dados!$B$1:$B$1993,H$7,Dados!$A$1:$A$1993,$A18) -> 0 | I18: =SUM(C18:H18) -> 0 | J18: =ROUND(I18*$L$4,2) -> 0 | K18: =SUM(I18:J18) -> 0 | L18: =K18+L17 -> 0
A19: =IF(DAY(A18)=20,DATE(YEAR(A18),MONTH(A18)+1,5),DATE(YEAR(A18),MONTH(A18),20)) -> 157 | B19: =B18+1 -> 11 | C19: =SUMIFS(Dados!$I$1:$I$1993,Dados!$B$1:$B$1993,C$7,Dados!$A$1:$A$1993,$A19) -> 0 | D19: =SUMIFS(Dados!$I$1:$I$1993,Dados!$B$1:$B$1993,D$7,Dados!$A$1:$A$1993,$A19) -> 0 | E19: =SUMIFS(Dados!$I$1:$I$1993,Dados!$B$1:$B$1993,E$7,Dados!$A$1:$A$1993,$A19) -> 0 | F19: =SUMIFS(Dados!$I$1:$I$1993,Dados!$B$1:$B$1993,F$7,Dados!$A$1:$A$1993,$A19) -> 0 | G19: =SUMIFS(Dados!$I$1:$I$1993,Dados!$B$1:$B$1993,G$7,Dados!$A$1:$A$1993,$A19) -> 0 | H19: =SUMIFS(Dados!$I$1:$I$1993,Dados!$B$1:$B$1993,H$7,Dados!$A$1:$A$1993,$A19) -> 0 | I19: =SUM(C19:H19) -> 0 | J19: =ROUND(I19*$L$4,2) -> 0 | K19: =SUM(I19:J19) -> 0 | L19: =K19+L18 -> 0
A20: =IF(DAY(A19)=20,DATE(YEAR(A19),MONTH(A19)+1,5),DATE(YEAR(A19),MONTH(A19),20)) -> 172 | B20: =B19+1 -> 12 | C20: =SUMIFS(Dados!$I$1:$I$1993,Dados!$B$1:$B$1993,C$7,Dados!$A$1:$A$1993,$A20) -> 0 | D20: =SUMIFS(Dados!$I$1:$I$1993,Dados!$B$1:$B$1993,D$7,Dados!$A$1:$A$1993,$A20) -> 0 | E20: =SUMIFS(Dados!$I$1:$I$1993,Dados!$B$1:$B$1993,E$7,Dados!$A$1:$A$1993,$A20) -> 0 | F20: =SUMIFS(Dados!$I$1:$I$1993,Dados!$B$1:$B$1993,F$7,Dados!$A$1:$A$1993,$A20) -> 0 | G20: =SUMIFS(Dados!$I$1:$I$1993,Dados!$B$1:$B$1993,G$7,Dados!$A$1:$A$1993,$A20) -> 0 | H20: =SUMIFS(Dados!$I$1:$I$1993,Dados!$B$1:$B$1993,H$7,Dados!$A$1:$A$1993,$A20) -> 0 | I20: =SUM(C20:H20) -> 0 | J20: =ROUND(I20*$L$4,2) -> 0 | K20: =SUM(I20:J20) -> 0 | L20: =K20+L19 -> 0
A21: =IF(DAY(A20)=20,DATE(YEAR(A20),MONTH(A20)+1,5),DATE(YEAR(A20),MONTH(A20),20)) -> 187 | B21: =B20+1 -> 13 | C21: =SUMIFS(Dados!$I$1:$I$1993,Dados!$B$1:$B$1993,C$7,Dados!$A$1:$A$1993,$A21) -> 0 | D21: =SUMIFS(Dados!$I$1:$I$1993,Dados!$B$1:$B$1993,D$7,Dados!$A$1:$A$1993,$A21) -> 0 | E21: =SUMIFS(Dados!$I$1:$I$1993,Dados!$B$1:$B$1993,E$7,Dados!$A$1:$A$1993,$A21) -> 0 | F21: =SUMIFS(Dados!$I$1:$I$1993,Dados!$B$1:$B$1993,F$7,Dados!$A$1:$A$1993,$A21) -> 0 | G21: =SUMIFS(Dados!$I$1:$I$1993,Dados!$B$1:$B$1993,G$7,Dados!$A$1:$A$1993,$A21) -> 0 | H21: =SUMIFS(Dados!$I$1:$I$1993,Dados!$B$1:$B$1993,H$7,Dados!$A$1:$A$1993,$A21) -> 0 | I21: =SUM(C21:H21) -> 0 | J21: =ROUND(I21*$L$4,2) -> 0 | K21: =SUM(I21:J21) -> 0 | L21: =K21+L20 -> 0
... A104: =IF(DAY(A103)=20,DATE(YEAR(A103),MONTH(A103)+1,5),DATE(YEAR(A103),MONTH(A103),20)) -> 1450 | B104: =B103+1 -> 96 | C104: =SUMIFS(Dados!$I$1:$I$1993,Dados!$B$1:$B$1993,C$7,Dados!$A$1:$A$1993,$A104) -> 0 | D104: =SUMIFS(Dados!$I$1:$I$1993,Dados!$B$1:$B$1993,D$7,Dados!$A$1:$A$1993,$A104) -> 0 | E104: =SUMIFS(Dados!$I$1:$I$1993,Dados!$B$1:$B$1993,E$7,Dados!$A$1:$A$1993,$A104) -> 0 | F104: =SUMIFS(Dados!$I$1:$I$1993,Dados!$B$1:$B$1993,F$7,Dados!$A$1:$A$1993,$A104) -> 0 | G104: =SUMIFS(Dados!$I$1:$I$1993,Dados!$B$1:$B$1993,G$7,Dados!$A$1:$A$1993,$A104) -> 0 | H104: =SUMIFS(Dados!$I$1:$I$1993,Dados!$B$1:$B$1993,H$7,Dados!$A$1:$A$1993,$A104) -> 0 | I104: =SUM(C104:H104) -> 0 | J104: =ROUND(I104*$L$4,2) -> 0 | K104: =SUM(I104:J104) -> 0 | L104: =K104+L103 -> 0
A105: TOTAL | C105: =SUM(C9:C104) -> 0 | D105: =SUM(D9:D104) -> 0 | E105: =SUM(E9:E104) -> 0 | F105: =SUM(F9:F104) -> 0 | G105: =SUM(G9:G104) -> 0 | H105: =SUM(H9:H104) -> 0 | I105: =SUM(I9:I104) -> 0 | J105: =SUM(J9:J104) -> 0 | K105: =SUM(K9:K104) -> 0

Sheet Tp.Despesas
G1: Rua Zodiaco, 87 Sala 07 – Santa Lúcia - Belo Horizonte - MG (31) 3654-6616 / (31) 99974-1241 / (31) 98711-1139 rvr.engenharia@gmail.com / vinicius.rinaldi26@gmail.com
A3: =RESUMO!A3 -> [NOME]
A4: =RESUMO!A4 -> [ENDEREÇO]
A6: RESUMO POR TIPO DE DESPESAS
C7: ADM | D7: DIV | E7: LOC | F7: MAT | G7: MO | H7: SERV | I7: TP
A8: DATA | C8: ADMINISTRATIVO | D8: DIVERSOS | E8: LOCAÇAO | F8: MATERIAL | G8: MÃO DE OBRA | H8: SERVIÇOS | I8: TARIFAS/TRIBUTOS PÚBLICAS | J8: TOTAL
A9: =DATE(YEAR(RESUMO!A9),MONTH(RESUMO!A9),1) -> 1 | C9: =SUMIFS(Dados!$I$1:$I$130,Dados!$K$1:$K$130,Tp.Despesas!C$7,Dados!$A$1:$A$130,">="&$A9,Dados!$A$1:$A$130,"<="&EOMONTH($A9,0)) -> 0 | D9: =SUMIFS(Dados!$I$1:$I$130,Dados!$K$1:$K$130,Tp.Despesas!D$7,Dados!$A$1:$A$130,">="&$A9,Dados!$A$1:$A$130,"<="&EOMONTH($A9,0)) -> 0 | E9: =SUMIFS(Dados!$I$1:$I$130,Dados!$K$1:$K$130,Tp.Despesas!E$7,Dados!$A$1:$A$130,">="&$A9,Dados!$A$1:$A$130,"<="&EOMONTH($A9,0)) -> 0 | F9: =SUMIFS(Dados!$I$1:$I$130,Dados!$K$1:$K$130,Tp.Despesas!F$7,Dados!$A$1:$A$130,">="&$A9,Dados!$A$1:$A$130,"<="&EOMONTH($A9,0)) -> 0 | G9: =SUMIFS(Dados!$I$1:$I$130,Dados!$K$1:$K$130,Tp.Despesas!G$7,Dados!$A$1:$A$130,">="&$A9,Dados!$A$1:$A$130,"<="&EOMONTH($A9,0)) -> 0 | H9: =SUMIFS(Dados!$I$1:$I$130,Dados!$K$1:$K$130,Tp.Despesas!H$7,Dados!$A$1:$A$130,">="&$A9,Dados!$A$1:$A$130,"<="&EOMONTH($A9,0)) -> 0 | I9: =SUMIFS(Dados!$I$1:$I$130,Dados!$K$1:$K$130,Tp.Despesas!I$7,Dados!$A$1:$A$130,">="&$A9,Dados!$A$1:$A$130,"<="&EOMONTH($A9,0)) -> 0 | J9: =SUM(C9:I9) -> 0
A10: =EOMONTH(A9,1)-DAY(EOMONTH(A9,1))+1 -> 32 | C10: =SUMIFS(Dados!$I$1:$I$1993,Dados!$K$1:$K$1993,Tp.Despesas!C$7,Dados!$J$1:$J$1993,">="&$A10,Dados!$J$1:$J$1993,"<="&EOMONTH($A10,0)) -> 0 | D10: =SUMIFS(Dados!$I$1:$I$1993,Dados!$K$1:$K$1993,Tp.Despesas!D$7,Dados!$J$1:$J$1993,">="&$A10,Dados!$J$1:$J$1993,"<="&EOMONTH($A10,0)) -> 0 | E10: =SUMIFS(Dados!$I$1:$I$1993,Dados!$K$1:$K$1993,Tp.Despesas!E$7,Dados!$J$1:$J$1993,">="&$A10,Dados!$J$1:$J$1993,"<="&EOMONTH($A10,0)) -> 0 | F10: =SUMIFS(Dados!$I$1:$I$1993,Dados!$K$1:$K$1993,Tp.Despesas!F$7,Dados!$J$1:$J$1993,">="&$A10,Dados!$J$1:$J$1993,"<="&EOMONTH($A10,0)) -> 0 | G10: =SUMIFS(Dados!$I$1:$I$1993,Dados!$K$1:$K$1993,Tp.Despesas!G$7,Dados!$J$1:$J$1993,">="&$A10,Dados!$J$1:$J$1993,"<="&EOMONTH($A10,0)) -> 0 | H10: =SUMIFS(Dados!$I$1:$I$1993,Dados!$K$1:$K$1993,Tp.Despesas!H$7,Dados!$J$1:$J$1993,">="&$A10,Dados!$J$1:$J$1993,"<="&EOMONTH($A10,0)) -> 0 | I10: =SUMIFS(Dados!$I$1:$I$1993,Dados!$K$1:$K$1993,Tp.Despesas!I$7,Dados!$J$1:$J$1993,">="&$A10,Dados!$J$1:$J$1993,"<="&EOMONTH($A10,0)) -> 0 | J10: =SUM(C10:I10) -> 0
A11: =EOMONTH(A10,1)-DAY(EOMONTH(A10,1))+1 -> 61 | C11: =SUMIFS(Dados!$I$1:$I$1993,Dados!$K$1:$K$1993,Tp.Despesas!C$7,Dados!$J$1:$J$1993,">="&$A11,Dados!$J$1:$J$1993,"<="&EOMONTH($A11,0)) -> 0 | D11: =SUMIFS(Dados!$I$1:$I$1993,Dados!$K$1:$K$1993,Tp.Despesas!D$7,Dados!$J$1:$J$1993,">="&$A11,Dados!$J$1:$J$1993,"<="&EOMONTH($A11,0)) -> 0 | E11: =SUMIFS(Dados!$I$1:$I$1993,Dados!$K$1:$K$1993,Tp.Despesas!E$7,Dados!$J$1:$J$1993,">="&$A11,Dados!$J$1:$J$1993,"<="&EOMONTH($A11,0)) -> 0 | F11: =SUMIFS(Dados!$I$1:$I$1993,Dados!$K$1:$K$1993,Tp.Despesas!F$7,Dados!$J$1:$J$1993,">="&$A11,Dados!$J$1:$J$1993,"<="&EOMONTH($A11,0)) -> 0 | G11: =SUMIFS(Dados!$I$1:$I$1993,Dados!$K$1:$K$1993,Tp.Despesas!G$7,Dados!$J$1:$J$1993,">="&$A11,Dados!$J$1:$J$1993,"<="&EOMONTH($A11,0)) -> 0 | H11: =SUMIFS(Dados!$I$1:$I$1993,Dados!$K$1:$K$1993,Tp.Despesas!H$7,Dados!$J$1:$J$1993,">="&$A11,Dados!$J$1:$J$1993,"<="&EOMONTH($A11,0)) -> 0 | I11: =SUMIFS(Dados!$I$1:$I$1993,Dados!$K$1:$K$1993,Tp.Despesas!I$7,Dados!$J$1:$J$1993,">="&$A11,Dados!$J$1:$J$1993,"<="&EOMONTH($A11,0)) -> 0 | J11: =SUM(C11:I11) -> 0
A12: =EOMONTH(A11,1)-DAY(EOMONTH(A11,1))+1 -> 92 | C12: =SUMIFS(Dados!$I$1:$I$1993,Dados!$K$1:$K$1993,Tp.Despesas!C$7,Dados!$J$1:$J$1993,">="&$A12,Dados!$J$1:$J$1993,"<="&EOMONTH($A12,0)) -> 0 | D12: =SUMIFS(Dados!$I$1:$I$1993,Dados!$K$1:$K$1993,Tp.Despesas!D$7,Dados!$J$1:$J$1993,">="&$A12,Dados!$J$1:$J$1993,"<="&EOMONTH($A12,0)) -> 0 | E12: =SUMIFS(Dados!$I$1:$I$1993,Dados!$K$1:$K$1993,Tp.Despesas!E$7,Dados!$J$1:$J$1993,">="&$A12,Dados!$J$1:$J$1993,"<="&EOMONTH($A12,0)) -> 0 | F12: =SUMIFS(Dados!$I$1:$I$1993,Dados!$K$1:$K$1993,Tp.Despesas!F$7,Dados!$J$1:$J$1993,">="&$A12,Dados!$J$1:$J$1993,"<="&EOMONTH($A12,0)) -> 0 | G12: =SUMIFS(Dados!$I$1:$I$1993,Dados!$K$1:$K$1993,Tp.Despesas!G$7,Dados!$J$1:$J$1993,">="&$A12,Dados!$J$1:$J$1993,"<="&EOMONTH($A12,0)) -> 0 | H12: =SUMIFS(Dados!$I$1:$I$1993,Dados!$K$1:$K$1993,Tp.Despesas!H$7,Dados!$J$1:$J$1993,">="&$A12,Dados!$J$1:$J$1993,"<="&EOMONTH($A12,0)) -> 0 | I12: =SUMIFS(Dados!$I$1:$I$1993,Dados!$K$1:$K$1993,Tp.Despesas!I$7,Dados!$J$1:$J$1993,">="&$A12,Dados!$J$1:$J$1993,"<="&EOMONTH($A12,0)) -> 0 | J12: =SUM(C12:I12) -> 0
A13: =EOMONTH(A12,1)-DAY(EOMONTH(A12,1))+1 -> 122 | C13: =SUMIFS(Dados!$I$1:$I$1993,Dados!$K$1:$K$1993,Tp.Despesas!C$7,Dados!$J$1:$J$1993,">="&$A13,Dados!$J$1:$J$1993,"<="&EOMONTH($A13,0)) -> 0 | D13: =SUMIFS(Dados!$I$1:$I$1993,Dados!$K$1:$K$1993,Tp.Despesas!D$7,Dados!$J$1:$J$1993,">="&$A13,Dados!$J$1:$J$1993,"<="&EOMONTH($A13,0)) -> 0 | E13: =SUMIFS(Dados!$I$1:$I$1993,Dados!$K$1:$K$1993,Tp.Despesas!E$7,Dados!$J$1:$J$1993,">="&$A13,Dados!$J$1:$J$1993,"<="&EOMONTH($A13,0)) -> 0 | F13: =SUMIFS(Dados!$I$1:$I$1993,Dados!$K$1:$K$1993,Tp.Despesas!F$7,Dados!$J$1:$J$1993,">="&$A13,Dados!$J$1:$J$1993,"<="&EOMONTH($A13,0)) -> 0 | G13: =SUMIFS(Dados!$I$1:$I$1993,Dados!$K$1:$K$1993,Tp.Despesas!G$7,Dados!$J$1:$J$1993,">="&$A13,Dados!$J$1:$J$1993,"<="&EOMONTH($A13,0)) -> 0 | H13: =SUMIFS(Dados!$I$1:$I$1993,Dados!$K$1:$K$1993,Tp.Despesas!H$7,Dados!$J$1:$J$1993,">="&$A13,Dados!$J$1:$J$1993,"<="&EOMONTH($A13,0)) -> 0 | I13: =SUMIFS(Dados!$I$1:$I$1993,Dados!$K$1:$K$1993,Tp.Despesas!I$7,Dados!$J$1:$J$1993,">="&$A13,Dados!$J$1:$J$1993,"<="&EOMONTH($A13,0)) -> 0 | J13: =SUM(C13:I13) -> 0
A14: =EOMONTH(A13,1)-DAY(EOMONTH(A13,1))+1 -> 153 | C14: =SUMIFS(Dados!$I$1:$I$1993,Dados!$K$1:$K$1993,Tp.Despesas!C$7,Dados!$J$1:$J$1993,">="&$A14,Dados!$J$1:$J$1993,"<="&EOMONTH($A14,0)) -> 0 | D14: =SUMIFS(Dados!$I$1:$I$1993,Dados!$K$1:$K$1993,Tp.Despesas!D$7,Dados!$J$1:$J$1993,">="&$A14,Dados!$J$1:$J$1993,"<="&EOMONTH($A14,0)) -> 0 | E14: =SUMIFS(Dados!$I$1:$I$1993,Dados!$K$1:$K$1993,Tp.Despesas!E$7,Dados!$J$1:$J$1993,">="&$A14,Dados!$J$1:$J$1993,"<="&EOMONTH($A14,0)) -> 0 | F14: =SUMIFS(Dados!$I$1:$I$1993,Dados!$K$1:$K$1993,Tp.Despesas!F$7,Dados!$J$1:$J$1993,">="&$A14,Dados!$J$1:$J$1993,"<="&EOMONTH($A14,0)) -> 0 | G14: =SUMIFS(Dados!$I$1:$I$1993,Dados!$K$1:$K$1993,Tp.Despesas!G$7,Dados!$J$1:$J$1993,">="&$A14,Dados!$J$1:$J$1993,"<="&EOMONTH($A14,0)) -> 0 | H14: =SUMIFS(Dados!$I$1:$I$1993,Dados!$K$1:$K$1993,Tp.Despesas!H$7,Dados!$J$1:$J$1993,">="&$A14,Dados!$J$1:$J$1993,"<="&EOMONTH($A14,0)) -> 0 | I14: =SUMIFS(Dados!$I$1:$I$1993,Dados!$K$1:$K$1993,Tp.Despesas!I$7,Dados!$J$1:$J$1993,">="&$A14,Dados!$J$1:$J$1993,"<="&EOMONTH($A14,0)) -> 0 | J14: =SUM(C14:I14) -> 0
A15: =EOMONTH(A14,1)-DAY(EOMONTH(A14,1))+1 -> 183 | C15: =SUMIFS(Dados!$I$1:$I$1993,Dados!$K$1:$K$1993,Tp.Despesas!C$7,Dados!$J$1:$J$1993,">="&$A15,Dados!$J$1:$J$1993,"<="&EOMONTH($A15,0)) -> 0 | D15: =SUMIFS(Dados!$I$1:$I$1993,Dados!$K$1:$K$1993,Tp.Despesas!D$7,Dados!$J$1:$J$1993,">="&$A15,Dados!$J$1:$J$1993,"<="&EOMONTH($A15,0)) -> 0 | E15: =SUMIFS(Dados!$I$1:$I$1993,Dados!$K$1:$K$1993,Tp.Despesas!E$7,Dados!$J$1:$J$1993,">="&$A15,Dados!$J$1:$J$1993,"<="&EOMONTH($A15,0)) -> 0 | F15: =SUMIFS(Dados!$I$1:$I$1993,Dados!$K$1:$K$1993,Tp.Despesas!F$7,Dados!$J$1:$J$1993,">="&$A15,Dados!$J$1:$J$1993,"<="&EOMONTH($A15,0)) -> 0 | G15: =SUMIFS(Dados!$I$1:$I$1993,Dados!$K$1:$K$1993,Tp.Despesas!G$7,Dados!$J$1:$J$1993,">="&$A15,Dados!$J$1:$J$1993,"<="&EOMONTH($A15,0)) -> 0 | H15: =SUMIFS(Dados!$I$1:$I$1993,Dados!$K$1:$K$1993,Tp.Despesas!H$7,Dados!$J$1:$J$1993,">="&$A15,Dados!$J$1:$J$1993,"<="&EOMONTH($A15,0)) -> 0 | I15: =SUMIFS(Dados!$I$1:$I$1993,Dados!$K$1:$K$1993,Tp.Despesas!I$7,Dados!$J$1:$J$1993,">="&$A15,Dados!$J$1:$J$1993,"<="&EOMONTH($A15,0)) -> 0 | J15: =SUM(C15:I15) -> 0
A16: =EOMONTH(A15,1)-DAY(EOMONTH(A15,1))+1 -> 214 | C16: =SUMIFS(Dados!$I$1:$I$1993,Dados!$K$1:$K$1993,Tp.Despesas!C$7,Dados!$J$1:$J$1993,">="&$A16,Dados!$J$1:$J$1993,"<="&EOMONTH($A16,0)) -> 0 | D16: =SUMIFS(Dados!$I$1:$I$1993,Dados!$K$1:$K$1993,Tp.Despesas!D$7,Dados!$J$1:$J$1993,">="&$A16,Dados!$J$1:$J$1993,"<="&EOMONTH($A16,0)) -> 0 | E16: =SUMIFS(Dados!$I$1:$I$1993,Dados!$K$1:$K$1993,Tp.Despesas!E$7,Dados!$J$1:$J$1993,">="&$A16,Dados!$J$1:$J$1993,"<="&EOMONTH($A16,0)) -> 0 | F16: =SUMIFS(Dados!$I$1:$I$1993,Dados!$K$1:$K$1993,Tp.Despesas!F$7,Dados!$J$1:$J$1993,">="&$A16,Dados!$J$1:$J$1993,"<="&EOMONTH($A16,0)) -> 0 | G16: =SUMIFS(Dados!$I$1:$I$1993,Dados!$K$1:$K$1993,Tp.Despesas!G$7,Dados!$J$1:$J$1993,">="&$A16,Dados!$J$1:$J$1993,"<="&EOMONTH($A16,0)) -> 0 | H16: =SUMIFS(Dados!$I$1:$I$1993,Dados!$K$1:$K$1993,Tp.Despesas!H$7,Dados!$J$1:$J$1993,">="&$A16,Dados!$J$1:$J$1993,"<="&EOMONTH($A16,0)) -> 0 | I16: =SUMIFS(Dados!$I$1:$I$1993,Dados!$K$1:$K$1993,Tp.Despesas!I$7,Dados!$J$1:$J$1993,">="&$A16,Dados!$J$1:$J$1993,"<="&EOMONTH($A16,0)) -> 0 | J16: =SUM(C16:I16) -> 0
A17: =EOMONTH(A16,1)-DAY(EOMONTH(A16,1))+1 -> 245 | C17: =SUMIFS(Dados!$I$1:$I$1993,Dados!$K$1:$K$1993,Tp.Despesas!C$7,Dados!$J$1:$J$1993,">="&$A17,Dados!$J$1:$J$1993,"<="&EOMONTH($A17,0)) -> 0 | D17: =SUMIFS(Dados!$I$1:$I$1993,Dados!$K$1:$K$1993,Tp.Despesas!D$7,Dados!$J$1:$J$1993,">="&$A17,Dados!$J$1:$J$1993,"<="&EOMONTH($A17,0)) -> 0 | E17: =SUMIFS(Dados!$I$1:$I$1993,Dados!$K$1:$K$1993,Tp.Despesas!E$7,Dados!$J$1:$J$1993,">="&$A17,Dados!$J$1:$J$1993,"<="&EOMONTH($A17,0)) -> 0 | F17: =SUMIFS(Dados!$I$1:$I$1993,Dados!$K$1:$K$1993,Tp.Despesas!F$7,Dados!$J$1:$J$1993,">="&$A17,Dados!$J$1:$J$1993,"<="&EOMONTH($A17,0)) -> 0 | G17: =SUMIFS(Dados!$I$1:$I$1993,Dados!$K$1:$K$1993,Tp.Despesas!G$7,Dados!$J$1:$J$1993,">="&$A17,Dados!$J$1:$J$1993,"<="&EOMONTH($A17,0)) -> 0 | H17: =SUMIFS(Dados!$I$1:$I$1993,Dados!$K$1:$K$1993,Tp.Despesas!H$7,Dados!$J$1:$J$1993,">="&$A17,Dados!$J$1:$J$1993,"<="&EOMONTH($A17,0)) -> 0 | I17: =SUMIFS(Dados!$I$1:$I$1993,Dados!$K$1:$K$1993,Tp.Despesas!I$7,Dados!$J$1:$J$1993,">="&$A17,Dados!$J$1:$J$1993,"<="&EOMONTH($A17,0)) -> 0 | J17: =SUM(C17:I17) -> 0
A18: =EOMONTH(A17,1)-DAY(EOMONTH(A17,1))+1 -> 275 | C18: =SUMIFS(Dados!$I$1:$I$1993,Dados!$K$1:$K$1993,Tp.Despesas!C$7,Dados!$J$1:$J$1993,">="&$A18,Dados!$J$1:$J$1993,"<="&EOMONTH($A18,0)) -> 0 | D18: =SUMIFS(Dados!$I$1:$I$1993,Dados!$K$1:$K$1993,Tp.Despesas!D$7,Dados!$J$1:$J$1993,">="&$A18,Dados!$J$1:$J$1993,"<="&EOMONTH($A18,0)) -> 0 | E18: =SUMIFS(Dados!$I$1:$I$1993,Dados!$K$1:$K$1993,Tp.Despesas!E$7,Dados!$J$1:$J$1993,">="&$A18,Dados!$J$1:$J$1993,"<="&EOMONTH($A18,0)) -> 0 | F18: =SUMIFS(Dados!$I$1:$I$1993,Dados!$K$1:$K$1993,Tp.Despesas!F$7,Dados!$J$1:$J$1993,">="&$A18,Dados!$J$1:$J$1993,"<="&EOMONTH($A18,0)) -> 0 | G18: =SUMIFS(Dados!$I$1:$I$1993,Dados!$K$1:$K$1993,Tp.Despesas!G$7,Dados!$J$1:$J$1993,">="&$A18,Dados!$J$1:$J$1993,"<="&EOMONTH($A18,0)) -> 0 | H18: =SUMIFS(Dados!$I$1:$I$1993,Dados!$K$1:$K$1993,Tp.Despesas!H$7,Dados!$J$1:$J$1993,">="&$A18,Dados!$J$1:$J$1993,"<="&EOMONTH($A18,0)) -> 0 | I18: =SUMIFS(Dados!$I$1:$I$1993,Dados!$K$1:$K$1993,Tp.Despesas!I$7,Dados!$J$1:$J$1993,">="&$A18,Dados!$J$1:$J$1993,"<="&EOMONTH($A18,0)) -> 0 | J18: =SUM(C18:I18) -> 0
A19: =EOMONTH(A18,1)-DAY(EOMONTH(A18,1))+1 -> 306 | C19: =SUMIFS(Dados!$I$1:$I$1993,Dados!$K$1:$K$1993,Tp.Despesas!C$7,Dados!$J$1:$J$1993,">="&$A19,Dados!$J$1:$J$1993,"<="&EOMONTH($A19,0)) -> 0 | D19: =SUMIFS(Dados!$I$1:$I$1993,Dados!$K$1:$K$1993,Tp.Despesas!D$7,Dados!$J$1:$J$1993,">="&$A19,Dados!$J$1:$J$1993,"<="&EOMONTH($A19,0)) -> 0 | E19: =SUMIFS(Dados!$I$1:$I$1993,Dados!$K$1:$K$1993,Tp.Despesas!E$7,Dados!$J$1:$J$1993,">="&$A19,Dados!$J$1:$J$1993,"<="&EOMONTH($A19,0)) -> 0 | F19: =SUMIFS(Dados!$I$1:$I$1993,Dados!$K$1:$K$1993,Tp.Despesas!F$7,Dados!$J$1:$J$1993,">="&$A19,Dados!$J$1:$J$1993,"<="&EOMONTH($A19,0)) -> 0 | G19: =SUMIFS(Dados!$I$1:$I$1993,Dados!$K$1:$K$1993,Tp.Despesas!G$7,Dados!$J$1:$J$1993,">="&$A19,Dados!$J$1:$J$1993,"<="&EOMONTH($A19,0)) -> 0 | H19: =SUMIFS(Dados!$I$1:$I$1993,Dados!$K$1:$K$1993,Tp.Despesas!H$7,Dados!$J$1:$J$1993,">="&$A19,Dados!$J$1:$J$1993,"<="&EOMONTH($A19,0)) -> 0 | I19: =SUMIFS(Dados!$I$1:$I$1993,Dados!$K$1:$K$1993,Tp.Despesas!I$7,Dados!$J$1:$J$1993,">="&$A19,Dados!$J$1:$J$1993,"<="&EOMONTH($A19,0)) -> 0 | J19: =SUM(C19:I19) -> 0
A20: =EOMONTH(A19,1)-DAY(EOMONTH(A19,1))+1 -> 336 | C20: =SUMIFS(Dados!$I$1:$I$1993,Dados!$K$1:$K$1993,Tp.Despesas!C$7,Dados!$J$1:$J$1993,">="&$A20,Dados!$J$1:$J$1993,"<="&EOMONTH($A20,0)) -> 0 | D20: =SUMIFS(Dados!$I$1:$I$1993,Dados!$K$1:$K$1993,Tp.Despesas!D$7,Dados!$J$1:$J$1993,">="&$A20,Dados!$J$1:$J$1993,"<="&EOMONTH($A20,0)) -> 0 | E20: =SUMIFS(Dados!$I$1:$I$1993,Dados!$K$1:$K$1993,Tp.Despesas!E$7,Dados!$J$1:$J$1993,">="&$A20,Dados!$J$1:$J$1993,"<="&EOMONTH($A20,0)) -> 0 | F20: =SUMIFS(Dados!$I$1:$I$1993,Dados!$K$1:$K$1993,Tp.Despesas!F$7,Dados!$J$1:$J$1993,">="&$A20,Dados!$J$1:$J$1993,"<="&EOMONTH($A20,0)) -> 0 | G20: =SUMIFS(Dados!$I$1:$I$1993,Dados!$K$1:$K$1993,Tp.Despesas!G$7,Dados!$J$1:$J$1993,">="&$A20,Dados!$J$1:$J$1993,"<="&EOMONTH($A20,0)) -> 0 | H20: =SUMIFS(Dados!$I$1:$I$1993,Dados!$K$1:$K$1993,Tp.Despesas!H$7,Dados!$J$1:$J$1993,">="&$A20,Dados!$J$1:$J$1993,"<="&EOMONTH($A20,0)) -> 0 | I20: =SUMIFS(Dados!$I$1:$I$1993,Dados!$K$1:$K$1993,Tp.Despesas!I$7,Dados!$J$1:$J$1993,">="&$A20,Dados!$J$1:$J$1993,"<="&EOMONTH($A20,0)) -> 0 | J20: =SUM(C20:I20) -> 0
A21: =EOMONTH(A20,1)-DAY(EOMONTH(A20,1))+1 -> 367 | C21: =SUMIFS(Dados!$I$1:$I$1993,Dados!$K$1:$K$1993,Tp.Despesas!C$7,Dados!$J$1:$J$1993,">="&$A21,Dados!$J$1:$J$1993,"<="&EOMONTH($A21,0)) -> 0 | D21: =SUMIFS(Dados!$I$1:$I$1993,Dados!$K$1:$K$1993,Tp.Despesas!D$7,Dados!$J$1:$J$1993,">="&$A21,Dados!$J$1:$J$1993,"<="&EOMONTH($A21,0)) -> 0 | E21: =SUMIFS(Dados!$I$1:$I$1993,Dados!$K$1:$K$1993,Tp.Despesas!E$7,Dados!$J$1:$J$1993,">="&$A21,Dados!$J$1:$J$1993,"<="&EOMONTH($A21,0)) -> 0 | F21: =SUMIFS(Dados!$I$1:$I$1993,Dados!$K$1:$K$1993,Tp.Despesas!F$7,Dados!$J$1:$J$1993,">="&$A21,Dados!$J$1:$J$1993,"<="&EOMONTH($A21,0)) -> 0 | G21: =SUMIFS(Dados!$I$1:$I$1993,Dados!$K$1:$K$1993,Tp.Despesas!G$7,Dados!$J$1:$J$1993,">="&$A21,Dados!$J$1:$J$1993,"<="&EOMONTH($A21,0)) -> 0 | H21: =SUMIFS(Dados!$I$1:$I$1993,Dados!$K$1:$K$1993,Tp.Despesas!H$7,Dados!$J$1:$J$1993,">="&$A21,Dados!$J$1:$J$1993,"<="&EOMONTH($A21,0)) -> 0 | I21: =SUMIFS(Dados!$I$1:$I$1993,Dados!$K$1:$K$1993,Tp.Despesas!I$7,Dados!$J$1:$J$1993,">="&$A21,Dados!$J$1:$J$1993,"<="&EOMONTH($A21,0)) -> 0 | J21: =SUM(C21:I21) -> 0
... A44: =EOMONTH(A43,1)-DAY(EOMONTH(A43,1))+1 -> 1066 | C44: =SUMIFS(Dados!$I$1:$I$1993,Dados!$K$1:$K$1993,Tp.Despesas!C$7,Dados!$J$1:$J$1993,">="&$A44,Dados!$J$1:$J$1993,"<="&EOMONTH($A44,0)) -> 0 | D44: =SUMIFS(Dados!$I$1:$I$1993,Dados!$K$1:$K$1993,Tp.Despesas!D$7,Dados!$J$1:$J$1993,">="&$A44,Dados!$J$1:$J$1993,"<="&EOMONTH($A44,0)) -> 0 | E44: =SUMIFS(Dados!$I$1:$I$1993,Dados!$K$1:$K$1993,Tp.Despesas!E$7,Dados!$J$1:$J$1993,">="&$A44,Dados!$J$1:$J$1993,"<="&EOMONTH($A44,0)) -> 0 | F44: =SUMIFS(Dados!$I$1:$I$1993,Dados!$K$1:$K$1993,Tp.Despesas!F$7,Dados!$J$1:$J$1993,">="&$A44,Dados!$J$1:$J$1993,"<="&EOMONTH($A44,0)) -> 0 | G44: =SUMIFS(Dados!$I$1:$I$1993,Dados!$K$1:$K$1993,Tp.Despesas!G$7,Dados!$J$1:$J$1993,">="&$A44,Dados!$J$1:$J$1993,"<="&EOMONTH($A44,0)) -> 0 | H44: =SUMIFS(Dados!$I$1:$I$1993,Dados!$K$1:$K$1993,Tp.Despesas!H$7,Dados!$J$1:$J$1993,">="&$A44,Dados!$J$1:$J$1993,"<="&EOMONTH($A44,0)) -> 0 | I44: =SUMIFS(Dados!$I$1:$I$1993,Dados!$K$1:$K$1993,Tp.Despesas!I$7,Dados!$J$1:$J$1993,">="&$A44,Dados!$J$1:$J$1993,"<="&EOMONTH($A44,0)) -> 0 | J44: =SUM(C44:I44) -> 0
A45: TOTAL GERAL | C45: =SUM(C9:C44) -> 0 | D45: =SUM(D9:D44) -> 0 | E45: =SUM(E9:E44) -> 0 | F45: =SUM(F9:F44) -> 0 | G45: =SUM(G9:G44) -> 0 | H45: =SUM(H9:H44) -> 0 | I45: =SUM(I9:I44) -> 0 | J45: =SUM(J9:J44) -> 0
C46: =C45/$J$45 -> #DIV/0! | D46: =D45/$J$45 -> #DIV/0! | E46: =E45/$J$45 -> #DIV/0! | F46: =F45/$J$45 -> #DIV/0! | G46: =G45/$J$45 -> #DIV/0! | H46: =H45/$J$45 -> #DIV/0! | I46: =I45/$J$45 -> #DIV/0! | J46: =J45/$J$45 -> #DIV/0!
J48: =RESUMO!L104 -> 0
J49: =J48-J45 -> 0
