Workbook

Sheet Dados
A1: DATA_REL | B1: TP_DESP | C1: CNPJ_CPF | D1: NOME | E1: REFERÊNCIA | F1: NF | G1: VR_UNIT | H1: DIAS | I1: VALOR | J1: DT_VENCTO | K1: CATEGORIA | L1: DADOS_BANCARIOS | M1: OBSERVAÇÃO | N1: NF? | O1: PAGTO | P1: CHECK | Q1: RELATÓRIO
A2: 45540 | B2: 1 | C2: 14758063613 | D2: IZAEL BISPO OLIVEIRA | E2: DIÁRIA | G2: 200 | H2: 3 | I2: 600 | J2: 06/09/2024 | K2: MO | L2: PIX: 14758063613 | N2: =IF(ISERROR(SEARCH("NF",E2,1)),"NÃO","SIM") | O2: =IF($B2=5,"SIM","") | P2: =A2&B2&C2&E2&G2&EDATE(J2,0) | Q2: =IF(A2=0,"",VLOOKUP($A2,RESUMO!$A$8:$B$83,2,FALSE))
A3: 45540 | B3: 1 | C3: 14020156662 | D3: WELLINGTON GOMES PAIVA | E3: DIÁRIA | G3: 200 | H3: 1 | I3: 200 | J3: 06/09/2024 | K3: MO | L3: PIX: 14020156662 | N3: =IF(ISERROR(SEARCH("NF",E3,1)),"NÃO","SIM") | O3: =IF($B3=5,"SIM","") | P3: =A3&B3&C3&E3&G3&EDATE(J3,0) | Q3: =IF(A3=0,"",VLOOKUP($A3,RESUMO!$A$8:$B$83,2,FALSE))
A4: 45540 | B4: 1 | C4: 12095122623 | D4: WANDERSON ROMUALDO DE SOUZA | E4: DIÁRIA | G4: 200 | H4: 5 | I4: 1000 | J4: 06/09/2024 | K4: MO | L4: PIX: 12095122623 | N4: =IF(ISERROR(SEARCH("NF",E4,1)),"NÃO","SIM") | O4: =IF($B4=5,"SIM","") | P4: =A4&B4&C4&E4&G4&EDATE(J4,0) | Q4: =IF(A4=0,"",VLOOKUP($A4,RESUMO!$A$8:$B$83,2,FALSE))
A5: 45540 | B5: 2 | C5: 07834753000141 | D5: ANCORA PAPELARIA | E5: PLOTAGENS - NF A EMITIR | G5: 432 | I5: 432 | J5: 06/09/2024 | K5: SERV | L5: PIX: ancorapapelaria@gmail.com | N5: =IF(ISERROR(SEARCH("NF",E5,1)),"NÃO","SIM") | O5: =IF($B5=5,"SIM","") | P5: =A5&B5&C5&E5&G5&EDATE(J5,0) | Q5: =IF(A5=0,"",VLOOKUP($A5,RESUMO!$A$8:$B$83,2,FALSE))
A6: 45540 | B6: 2 | C6: 07834753000141 | D6: ANCORA PAPELARIA | E6: PLOTAGENS - NF A EMITIR | G6: 76 | I6: 76 | J6: 06/09/2024 | K6: SERV | L6: PIX: ancorapapelaria@gmail.com | N6: =IF(ISERROR(SEARCH("NF",E6,1)),"NÃO","SIM") | O6: =IF($B6=5,"SIM","") | P6: =A6&B6&C6&E6&G6&EDATE(J6,0) | Q6: =IF(A6=0,"",VLOOKUP($A6,RESUMO!$A$8:$B$83,2,FALSE))
A7: 45540 | B7: 2 | C7: 73586986653 | D7: RICARDO JOSE ELOY | E7: MARCAÇÃO DE TOPOGRAFIA | G7: 2000 | I7: 2000 | J7: 06/09/2024 | K7: SERV | L7: ITAÚ 5636 118738 - CPF: 73.586.986.6-53 | N7: =IF(ISERROR(SEARCH("NF",E7,1)),"NÃO","SIM") | O7: =IF($B7=5,"SIM","") | P7: =A7&B7&C7&E7&G7&EDATE(J7,0) | Q7: =IF(A7=0,"",VLOOKUP($A7,RESUMO!$A$8:$B$83,2,FALSE))
A8: 45540 | B8: 3 | C8: 46423467000145 | D8: MR DESENTUPIDORA | E8: BANHEIRO QUIMICO - NF 1189 | G8: 1300 | I8: 1300 | J8: 16/09/2024 | K8: MAT | N8: =IF(ISERROR(SEARCH("NF",E8,1)),"NÃO","SIM") | O8: =IF($B8=5,"SIM","") | P8: =A8&B8&C8&E8&G8&EDATE(J8,0) | Q8: =IF(A8=0,"",VLOOKUP($A8,RESUMO!$A$8:$B$83,2,FALSE))
A9: 45540 | B9: 4 | C9: 27648990687 | D9: ROGÉRIO VASCONCELOS SANTOS | E9: REGISTRO DE IMÓVEIS 24/05 - REEMBOLSO | G9: 38.77 | I9: 38.77 | J9: 24/05/2024 | K9: MO | L9: PIX: 31995901635 | N9: =IF(ISERROR(SEARCH("NF",E9,1)),"NÃO","SIM") | O9: =IF($B9=5,"SIM","") | P9: =A9&B9&C9&E9&G9&EDATE(J9,0) | Q9: =IF(A9=0,"",VLOOKUP($A9,RESUMO!$A$8:$B$83,2,FALSE))
A10: 45540 | B10: 5 | C10: 43828098000182 | D10: MADESCOM MADEIREIRA | E10: PONTALETE - PED. 47.192 | G10: 1265 | I10: 1265 | J10: 16/08/2024 | K10: MAT | N10: =IF(ISERROR(SEARCH("NF",E10,1)),"NÃO","SIM") | O10: =IF($B10=5,"SIM","") | P10: =A10&B10&C10&E10&G10&EDATE(J10,0) | Q10: =IF(A10=0,"",VLOOKUP($A10,RESUMO!$A$8:$B$83,2,FALSE))
A11: 45540 | B11: 5 | C11: 18850040000279 | D11: CASA DAS LONAS LTDA | E11: LONA AGRICOLA - NF 28110 | G11: 1788 | I11: 1788 | J11: 21/08/2024 | K11: MAT | N11: =IF(ISERROR(SEARCH("NF",E11,1)),"NÃO","SIM") | O11: =IF($B11=5,"SIM","") | P11: =A11&B11&C11&E11&G11&EDATE(J11,0) | Q11: =IF(A11=0,"",VLOOKUP($A11,RESUMO!$A$8:$B$83,2,FALSE))
A12: 45540 | B12: 5 | C12: 15746193000100 | D12: TRILHA DE MINAS | E12: SINAL - 30% TERRAPLANAGEM | G12: 70000 | I12: 70000 | J12: 29/08/2024 | K12: SERV | N12: =IF(ISERROR(SEARCH("NF",E12,1)),"NÃO","SIM") | O12: =IF($B12=5,"SIM","") | P12: =A12&B12&C12&E12&G12&EDATE(J12,0) | Q12: =IF(A12=0,"",VLOOKUP($A12,RESUMO!$A$8:$B$83,2,FALSE))
A13: 45540 | B13: 7 | C13: 30104762000107 | D13: VASCONCELOS & RINALDI ENGENHARIA | E13: ADM 13% - NF A EMITIR | G13: 10230.97 | I13: 10230.97 | J13: 06/09/2024 | K13: ADM | L13: PIX: 30104762000107 | N13: =IF(ISERROR(SEARCH("NF",E13,1)),"NÃO","SIM") | O13: =IF($B13=5,"SIM","") | P13: =A13&B13&C13&E13&G13&EDATE(J13,0) | Q13: =IF(A13=0,"",VLOOKUP($A13,RESUMO!$A$8:$B$83,2,FALSE))
A14: 45555 | B14: 1 | C14: 14758063613 | D14: IZAEL BISPO OLIVEIRA | E14: DIÁRIA | G14: 200 | H14: 10 | I14: 2000 | J14: 20/09/2024 | K14: MO | L14: PIX: 14758063613 | N14: =IF(ISERROR(SEARCH("NF",E14,1)),"NÃO","SIM") | O14: =IF($B14=5,"SIM","") | P14: =A14&B14&C14&E14&G14&EDATE(J14,0) | Q14: =IF(A14=0,"",VLOOKUP($A14,RESUMO!$A$8:$B$83,2,FALSE))
A15: 45555 | B15: 1 | C15: 31699502668 | D15: ANTONIO ZEFERINO LEANDRO | E15: DIÁRIA | G15: 200 | H15: 7 | I15: 1400 | J15: 20/09/2024 | K15: MO | L15: PIX: 31699502668 | N15: =IF(ISERROR(SEARCH("NF",E15,1)),"NÃO","SIM") | O15: =IF($B15=5,"SIM","") | P15: =A15&B15&C15&E15&G15&EDATE(J15,0) | Q15: =IF(A15=0,"",VLOOKUP($A15,RESUMO!$A$8:$B$83,2,FALSE))
A16: 45555 | B16: 2 | C16: 73586986653 | D16: RICARDO JOSE ELOY | E16: MARCAÇÃO DE TOPOGRAFIA | G16: 1200 | I16: 1200 | J16: 20/09/2024 | K16: SERV | L16: ITAÚ 5636 118738 - CPF: 73.586.986.6-53 | N16: =IF(ISERROR(SEARCH("NF",E16,1)),"NÃO","SIM") | O16: =IF($B16=5,"SIM","") | P16: =A16&B16&C16&E16&G16&EDATE(J16,0) | Q16: =IF(A16=0,"",VLOOKUP($A16,RESUMO!$A$8:$B$83,2,FALSE))
A17: 45555 | B17: 3 | C17: 32392731000116 | D17: DEPÓSITO 040 | E17: MATERIAIS DIVERSOS - NF 1323 | G17: 967.3 | I17: 967.3 | J17: 27/09/2024 | K17: MAT | N17: =IF(ISERROR(SEARCH("NF",E17,1)),"NÃO","SIM") | O17: =IF($B17=5,"SIM","") | P17: =A17&B17&C17&E17&G17&EDATE(J17,0) | Q17: =IF(A17=0,"",VLOOKUP($A17,RESUMO!$A$8:$B$83,2,FALSE))
A18: 45555 | B18: 5 | C18: 15746193000100 | D18: TRILHA DE MINAS | E18: SERVIÇO TERRAPLANGEM - NF 512 | G18: 60000 | I18: 60000 | J18: 11/09/2024 | K18: SERV | N18: =IF(ISERROR(SEARCH("NF",E18,1)),"NÃO","SIM") | O18: =IF($B18=5,"SIM","") | P18: =A18&B18&C18&E18&G18&EDATE(J18,0) | Q18: =IF(A18=0,"",VLOOKUP($A18,RESUMO!$A$8:$B$83,2,FALSE))
A19: 45555 | B19: 5 | C19: 00064354600 | D19: ORIDES ELOI DE OLIVEIRA NETO | E19: RETIRADA CORTINAS | G19: 5134 | I19: 5134 | J19: 12/09/2024 | K19: SERV | N19: =IF(ISERROR(SEARCH("NF",E19,1)),"NÃO","SIM") | O19: =IF($B19=5,"SIM","") | P19: =A19&B19&C19&E19&G19&EDATE(J19,0) | Q19: =IF(A19=0,"",VLOOKUP($A19,RESUMO!$A$8:$B$83,2,FALSE))
A20: 45555 | B20: 5 | C20: 10272028000131 | D20: MASTER SOUND | E20: RETIRADA EQUIP. AUDIO | G20: 890 | I20: 890 | J20: 12/09/2024 | K20: MAT | N20: =IF(ISERROR(SEARCH("NF",E20,1)),"NÃO","SIM") | O20: =IF($B20=5,"SIM","") | P20: =A20&B20&C20&E20&G20&EDATE(J20,0) | Q20: =IF(A20=0,"",VLOOKUP($A20,RESUMO!$A$8:$B$83,2,FALSE))
A21: 45555 | B21: 5 | C21: 04704622000151 | D21: PROJETART MOVEIS | E21: DESMONTAGEM MOVEIS - NF 152 | G21: 1600 | I21: 1600 | J21: 13/09/2024 | K21: MAT | N21: =IF(ISERROR(SEARCH("NF",E21,1)),"NÃO","SIM") | O21: =IF($B21=5,"SIM","") | P21: =A21&B21&C21&E21&G21&EDATE(J21,0) | Q21: =IF(A21=0,"",VLOOKUP($A21,RESUMO!$A$8:$B$83,2,FALSE))
A22: 45555 | B22: 7 | C22: 30104762000107 | D22: VASCONCELOS & RINALDI ENGENHARIA | E22: ADM 13% - NF A EMITIR | G22: 9514.87 | I22: 9514.87 | J22: 20/09/2024 | K22: ADM | L22: PIX: 30104762000107 | N22: =IF(ISERROR(SEARCH("NF",E22,1)),"NÃO","SIM") | O22: =IF($B22=5,"SIM","") | P22: =A22&B22&C22&E22&G22&EDATE(J22,0) | Q22: =IF(A22=0,"",VLOOKUP($A22,RESUMO!$A$8:$B$83,2,FALSE))
A23: 45570 | B23: 1 | C23: 14758063613 | D23: IZAEL BISPO OLIVEIRA | E23: DIÁRIA | G23: 200 | H23: 10 | I23: 2000 | J23: 04/10/2024 | K23: MO | L23: PIX: 14758063613 | N23: =IF(ISERROR(SEARCH("NF",E23,1)),"NÃO","SIM") | O23: =IF($B23=5,"SIM","") | P23: =A23&B23&C23&E23&G23&EDATE(J23,0) | Q23: =IF(A23=0,"",VLOOKUP($A23,RESUMO!$A$8:$B$83,2,FALSE))
A24: 45570 | B24: 2 | C24: 07834753000141 | D24: ANCORA PAPELARIA | E24: PLOTAGENS - NF A EMITIR | G24: 572 | I24: 572 | J24: 04/10/2024 | K24: SERV | L24: PIX: ancorapapelaria@gmail.com | N24: =IF(ISERROR(SEARCH("NF",E24,1)),"NÃO","SIM") | O24: =IF($B24=5,"SIM","") | P24: =A24&B24&C24&E24&G24&EDATE(J24,0) | Q24: =IF(A24=0,"",VLOOKUP($A24,RESUMO!$A$8:$B$83,2,FALSE))
A25: 45570 | B25: 2 | C25: 00000011207 | D25: MOTOBOY | E25: COMPETENCIA 09/2024 | G25: 135 | I25: 135 | J25: 04/10/2024 | K25: DIV | L25: PIX: 31995901635 | N25: =IF(ISERROR(SEARCH("NF",E25,1)),"NÃO","SIM") | O25: =IF($B25=5,"SIM","") | P25: =A25&B25&C25&E25&G25&EDATE(J25,0) | Q25: =IF(A25=0,"",VLOOKUP($A25,RESUMO!$A$8:$B$83,2,FALSE))
A26: 45570 | B26: 3 | C26: 42979237000378 | D26: TECFER COM E IND DE FERRO E MAT CONSTR LTDA | E26: TELHA, PREGO, ARAME - NF A EMITIR | G26: 5197.39 | I26: 5197.39 | J26: 04/10/2024 | K26: MAT | N26: =IF(ISERROR(SEARCH("NF",E26,1)),"NÃO","SIM") | O26: =IF($B26=5,"SIM","") | P26: =A26&B26&C26&E26&G26&EDATE(J26,0) | Q26: =IF(A26=0,"",VLOOKUP($A26,RESUMO!$A$8:$B$83,2,FALSE))
A27: 45570 | B27: 3 | C27: 46423467000145 | D27: MR DESENTUPIDORA | E27: LOCAÇÃO DE BANHEIRO - FL 1392 | G27: 1300 | I27: 1300 | J27: 16/10/2024 | K27: MAT | N27: =IF(ISERROR(SEARCH("NF",E27,1)),"NÃO","SIM") | O27: =IF($B27=5,"SIM","") | P27: =A27&B27&C27&E27&G27&EDATE(J27,0) | Q27: =IF(A27=0,"",VLOOKUP($A27,RESUMO!$A$8:$B$83,2,FALSE))
A28: 45570 | B28: 3 | C28: 07409393000130 | D28: LOCFER | E28: MARTELO - NF 26128 | G28: 320 | I28: 320 | J28: 17/10/2024 | K28: LOC | N28: =IF(ISERROR(SEARCH("NF",E28,1)),"NÃO","SIM") | O28: =IF($B28=5,"SIM","") | P28: =A28&B28&C28&E28&G28&EDATE(J28,0) | Q28: =IF(A28=0,"",VLOOKUP($A28,RESUMO!$A$8:$B$83,2,FALSE))
A29: 45570 | B29: 5 | C29: 03891863683 | D29: LEANDRO ALVES | E29: ELETRICISTA | G29: 400 | I29: 400 | J29: 17/09/2024 | K29: SERV | N29: =IF(ISERROR(SEARCH("NF",E29,1)),"NÃO","SIM") | O29: =IF($B29=5,"SIM","") | P29: =A29&B29&C29&E29&G29&EDATE(J29,0) | Q29: =IF(A29=0,"",VLOOKUP($A29,RESUMO!$A$8:$B$83,2,FALSE))
A30: 45570 | B30: 5 | C30: 15746193000100 | D30: TRILHA DE MINAS | E30: TERRAPLANAGEM - NF 520 | G30: 135250 | I30: 135250 | J30: 25/09/2024 | K30: SERV | N30: =IF(ISERROR(SEARCH("NF",E30,1)),"NÃO","SIM") | O30: =IF($B30=5,"SIM","") | P30: =A30&B30&C30&E30&G30&EDATE(J30,0) | Q30: =IF(A30=0,"",VLOOKUP($A30,RESUMO!$A$8:$B$83,2,FALSE))
A31: 45570 | B31: 7 | C31: 30104762000107 | D31: VASCONCELOS & RINALDI ENGENHARIA | E31: ADM 13% - NF A EMITIR | G31: 18872.67 | I31: 18872.67 | J31: 04/10/2024 | K31: ADM | L31: PIX: 30104762000107 | N31: =IF(ISERROR(SEARCH("NF",E31,1)),"NÃO","SIM") | O31: =IF($B31=5,"SIM","") | P31: =A31&B31&C31&E31&G31&EDATE(J31,0) | Q31: =IF(A31=0,"",VLOOKUP($A31,RESUMO!$A$8:$B$83,2,FALSE))
A32: 45585 | B32: 1 | C32: 07573876670 | D32: BRUNO JUNIO DA SILVA | E32: SALÁRIO | G32: 2080 | I32: 2080 | J32: 18/10/2024 | K32: MO | L32: PIX: 07573876670 | N32: =IF(ISERROR(SEARCH("NF",E32,1)),"NÃO","SIM") | O32: =IF($B32=5,"SIM","") | P32: =A32&B32&C32&E32&G32&EDATE(J32,0) | Q32: =IF(A32=0,"",VLOOKUP($A32,RESUMO!$A$8:$B$83,2,FALSE))
A33: 45585 | B33: 1 | C33: 00354432605 | D33: ANTONIO DUTRA DE FREITAS | E33: SALÁRIO | G33: 883.84 | I33: 883.84 | J33: 18/10/2024 | K33: MO | L33: PIX: 31982618378 | N33: =IF(ISERROR(SEARCH("NF",E33,1)),"NÃO","SIM") | O33: =IF($B33=5,"SIM","") | P33: =A33&B33&C33&E33&G33&EDATE(J33,0) | Q33: =IF(A33=0,"",VLOOKUP($A33,RESUMO!$A$8:$B$83,2,FALSE))
A34: 45585 | B34: 1 | C34: 07249031600 | D34: EDER PEREIRA DA SILVA | E34: SALÁRIO | G34: 883.84 | I34: 883.84 | J34: 18/10/2024 | K34: MO | L34: PIX: 07249031600 | N34: =IF(ISERROR(SEARCH("NF",E34,1)),"NÃO","SIM") | O34: =IF($B34=5,"SIM","") | P34: =A34&B34&C34&E34&G34&EDATE(J34,0) | Q34: =IF(A34=0,"",VLOOKUP($A34,RESUMO!$A$8:$B$83,2,FALSE))
A35: 45585 | B35: 1 | C35: 14758063613 | D35: IZAEL BISPO OLIVEIRA | E35: SALÁRIO | G35: 883.84 | I35: 883.84 | J35: 18/10/2024 | K35: MO | L35: PIX: 14758063613 | N35: =IF(ISERROR(SEARCH("NF",E35,1)),"NÃO","SIM") | O35: =IF($B35=5,"SIM","") | P35: =A35&B35&C35&E35&G35&EDATE(J35,0) | Q35: =IF(A35=0,"",VLOOKUP($A35,RESUMO!$A$8:$B$83,2,FALSE))
A36: 45585 | B36: 1 | C36: 85086894387 | D36: ROBEVAL PORTACIO DOS SANTOS | E36: SALÁRIO | G36: 514.24 | I36: 514.24 | J36: 18/10/2024 | K36: MO | L36: PIX: 31971706400 | N36: =IF(ISERROR(SEARCH("NF",E36,1)),"NÃO","SIM") | O36: =IF($B36=5,"SIM","") | P36: =A36&B36&C36&E36&G36&EDATE(J36,0) | Q36: =IF(A36=0,"",VLOOKUP($A36,RESUMO!$A$8:$B$83,2,FALSE))
A37: 45585 | B37: 1 | C37: 87942119653 | D37: DOMINGOS DA SILVA LIMA | E37: SALÁRIO | G37: 514.24 | I37: 514.24 | J37: 18/10/2024 | K37: MO | L37: CEF 013 0892 00113057-1 - CPF: 87.942.119.6-53 | N37: =IF(ISERROR(SEARCH("NF",E37,1)),"NÃO","SIM") | O37: =IF($B37=5,"SIM","") | P37: =A37&B37&C37&E37&G37&EDATE(J37,0) | Q37: =IF(A37=0,"",VLOOKUP($A37,RESUMO!$A$8:$B$83,2,FALSE))
A38: 45585 | B38: 1 | C38: 75746980315 | D38: FRANCISCO REGO DA SILVA | E38: SALÁRIO | G38: 732.8 | I38: 732.8 | J38: 18/10/2024 | K38: MO | L38: PIX: 75746980315 | N38: =IF(ISERROR(SEARCH("NF",E38,1)),"NÃO","SIM") | O38: =IF($B38=5,"SIM","") | P38: =A38&B38&C38&E38&G38&EDATE(J38,0) | Q38: =IF(A38=0,"",VLOOKUP($A38,RESUMO!$A$8:$B$83,2,FALSE))
A39: 45585 | B39: 1 | C39: 07573876670 | D39: BRUNO JUNIO DA SILVA | E39: DIÁRIA | G39: 365 | H39: 6 | I39: 2190 | J39: 18/10/2024 | K39: MO | L39: PIX: 07573876670 | N39: =IF(ISERROR(SEARCH("NF",E39,1)),"NÃO","SIM") | O39: =IF($B39=5,"SIM","") | P39: =A39&B39&C39&E39&G39&EDATE(J39,0) | Q39: =IF(A39=0,"",VLOOKUP($A39,RESUMO!$A$8:$B$83,2,FALSE))
A40: 45585 | B40: 1 | C40: 14758063613 | D40: IZAEL BISPO OLIVEIRA | E40: DIÁRIA | G40: 215 | H40: 5 | I40: 1075 | J40: 18/10/2024 | K40: MO | L40: PIX: 14758063613 | N40: =IF(ISERROR(SEARCH("NF",E40,1)),"NÃO","SIM") | O40: =IF($B40=5,"SIM","") | P40: =A40&B40&C40&E40&G40&EDATE(J40,0) | Q40: =IF(A40=0,"",VLOOKUP($A40,RESUMO!$A$8:$B$83,2,FALSE))
A41: 45585 | B41: 1 | C41: 07249031600 | D41: EDER PEREIRA DA SILVA | E41: DIÁRIA | G41: 215 | H41: 5 | I41: 1075 | J41: 18/10/2024 | K41: MO | L41: PIX: 07249031600 | N41: =IF(ISERROR(SEARCH("NF",E41,1)),"NÃO","SIM") | O41: =IF($B41=5,"SIM","") | P41: =A41&B41&C41&E41&G41&EDATE(J41,0) | Q41: =IF(A41=0,"",VLOOKUP($A41,RESUMO!$A$8:$B$83,2,FALSE))
A42: 45585 | B42: 1 | C42: 00354432605 | D42: ANTONIO DUTRA DE FREITAS | E42: DIÁRIA | G42: 215 | H42: 5 | I42: 1075 | J42: 18/10/2024 | K42: MO | L42: PIX: 31982618378 | N42: =IF(ISERROR(SEARCH("NF",E42,1)),"NÃO","SIM") | O42: =IF($B42=5,"SIM","") | P42: =A42&B42&C42&E42&G42&EDATE(J42,0) | Q42: =IF(A42=0,"",VLOOKUP($A42,RESUMO!$A$8:$B$83,2,FALSE))
A43: 45585 | B43: 1 | C43: 75746980315 | D43: FRANCISCO REGO DA SILVA | E43: DIÁRIA | G43: 175 | H43: 6 | I43: 1050 | J43: 18/10/2024 | K43: MO | L43: PIX: 75746980315 | N43: =IF(ISERROR(SEARCH("NF",E43,1)),"NÃO","SIM") | O43: =IF($B43=5,"SIM","") | P43: =A43&B43&C43&E43&G43&EDATE(J43,0) | Q43: =IF(A43=0,"",VLOOKUP($A43,RESUMO!$A$8:$B$83,2,FALSE))
A44: 45585 | B44: 1 | C44: 87942119653 | D44: DOMINGOS DA SILVA LIMA | E44: DIÁRIA | G44: 135 | H44: 5 | I44: 675 | J44: 18/10/2024 | K44: MO | L44: CEF 013 0892 00113057-1 - CPF: 87.942.119.6-53 | N44: =IF(ISERROR(SEARCH("NF",E44,1)),"NÃO","SIM") | O44: =IF($B44=5,"SIM","") | P44: =A44&B44&C44&E44&G44&EDATE(J44,0) | Q44: =IF(A44=0,"",VLOOKUP($A44,RESUMO!$A$8:$B$83,2,FALSE))
A45: 45585 | B45: 1 | C45: 85086894387 | D45: ROBEVAL PORTACIO DOS SANTOS | E45: DIÁRIA | G45: 135 | H45: 5 | I45: 675 | J45: 18/10/2024 | K45: MO | L45: PIX: 31971706400 | N45: =IF(ISERROR(SEARCH("NF",E45,1)),"NÃO","SIM") | O45: =IF($B45=5,"SIM","") | P45: =A45&B45&C45&E45&G45&EDATE(J45,0) | Q45: =IF(A45=0,"",VLOOKUP($A45,RESUMO!$A$8:$B$83,2,FALSE))
A46: 45585 | B46: 2 | C46: 37052904870 | D46: VR AREIA E BRITA | E46: AREIA E BRITA - PED. 4910 / 4916 / 4924 | G46: 4650 | I46: 4650 | J46: 18/10/2024 | K46: MAT | L46: C6 BANK 0001 19363893 - CPF: 37.052.904.8-70 | N46: =IF(ISERROR(SEARCH("NF",E46,1)),"NÃO","SIM") | O46: =IF($B46=5,"SIM","") | P46: =A46&B46&C46&E46&G46&EDATE(J46,0) | Q46: =IF(A46=0,"",VLOOKUP($A46,RESUMO!$A$8:$B$83,2,FALSE))
A47: 45585 | B47: 2 | C47: 07429259600 | D47: AMARO CESARIO DA SILVA | E47: FECHAMENTO DRY WAL COZINHA E SALA | G47: 2150 | I47: 2150 | J47: 18/10/2024 | K47: SERV | L47: PIX: 07429259600 | N47: =IF(ISERROR(SEARCH("NF",E47,1)),"NÃO","SIM") | O47: =IF($B47=5,"SIM","") | P47: =A47&B47&C47&E47&G47&EDATE(J47,0) | Q47: =IF(A47=0,"",VLOOKUP($A47,RESUMO!$A$8:$B$83,2,FALSE))
A48: 45585 | B48: 3 | C48: 07409393000130 | D48: LOCFER | E48: SERRA MADEIRA E SERRA BANCADA - NF 26353 | G48: 640 | I48: 640 | J48: 04/11/2024 | K48: LOC | N48: =IF(ISERROR(SEARCH("NF",E48,1)),"NÃO","SIM") | O48: =IF($B48=5,"SIM","") | P48: =A48&B48&C48&E48&G48&EDATE(J48,0) | Q48: =IF(A48=0,"",VLOOKUP($A48,RESUMO!$A$8:$B$83,2,FALSE))
A49: 45585 | B49: 3 | C49: 07409393000130 | D49: LOCFER | E49: SERRA E BROCAS - NF 2766 | G49: 740.4 | I49: 740.4 | J49: 05/11/2024 | K49: LOC | N49: =IF(ISERROR(SEARCH("NF",E49,1)),"NÃO","SIM") | O49: =IF($B49=5,"SIM","") | P49: =A49&B49&C49&E49&G49&EDATE(J49,0) | Q49: =IF(A49=0,"",VLOOKUP($A49,RESUMO!$A$8:$B$83,2,FALSE))
A50: 45585 | B50: 3 | C50: 21944558000103 | D50: LOCAN ANDAIMES | E50: LOCAÇÃO DE ANDAIMES - ND 9872 | G50: 528 | I50: 528 | J50: 21/10/2024 | K50: LOC | N50: =IF(ISERROR(SEARCH("NF",E50,1)),"NÃO","SIM") | O50: =IF($B50=5,"SIM","") | P50: =A50&B50&C50&E50&G50&EDATE(J50,0) | Q50: =IF(A50=0,"",VLOOKUP($A50,RESUMO!$A$8:$B$83,2,FALSE))
A51: 45585 | B51: 3 | C51: 32392731000116 | D51: DEPÓSITO 040 | E51: SACO E LONA - NF 3041 | G51: 1330 | I51: 1330 | J51: 21/10/2024 | K51: MAT | N51: =IF(ISERROR(SEARCH("NF",E51,1)),"NÃO","SIM") | O51: =IF($B51=5,"SIM","") | P51: =A51&B51&C51&E51&G51&EDATE(J51,0) | Q51: =IF(A51=0,"",VLOOKUP($A51,RESUMO!$A$8:$B$83,2,FALSE))
A52: 45585 | B52: 3 | C52: 17581836000634 | D52: LOJA DO PAULO | E52: CADEADO, CORRENTE - NF 31267 | G52: 477.4 | I52: 477.4 | J52: 22/10/2024 | K52: MAT | N52: =IF(ISERROR(SEARCH("NF",E52,1)),"NÃO","SIM") | O52: =IF($B52=5,"SIM","") | P52: =A52&B52&C52&E52&G52&EDATE(J52,0) | Q52: =IF(A52=0,"",VLOOKUP($A52,RESUMO!$A$8:$B$83,2,FALSE))
A53: 45585 | B53: 3 | C53: 42542081000100 | D53: MADEX MADEIRAS E COMPENSADOS LTDA | E53: MADEIRAS - NF 5942 - PARC. 1/2 | G53: 11481 | I53: 11481 | J53: 22/10/2024 | K53: MAT | N53: =IF(ISERROR(SEARCH("NF",E53,1)),"NÃO","SIM") | O53: =IF($B53=5,"SIM","") | P53: =A53&B53&C53&E53&G53&EDATE(J53,0) | Q53: =IF(A53=0,"",VLOOKUP($A53,RESUMO!$A$8:$B$83,2,FALSE))
A54: 45585 | B54: 3 | C54: 07409393000130 | D54: LOCFER | E54: ESMERILHADEIRA - NF 26199 | G54: 100 | I54: 100 | J54: 23/10/2024 | K54: LOC | N54: =IF(ISERROR(SEARCH("NF",E54,1)),"NÃO","SIM") | O54: =IF($B54=5,"SIM","") | P54: =A54&B54&C54&E54&G54&EDATE(J54,0) | Q54: =IF(A54=0,"",VLOOKUP($A54,RESUMO!$A$8:$B$83,2,FALSE))
A55: 45585 | B55: 3 | C55: 14072798002720 | D55: NOSSA LOJA | E55: ROLO, TINTAS, TRINCHA - NF 5115 | G55: 372 | I55: 372 | J55: 31/10/2024 | K55: MAT | N55: =IF(ISERROR(SEARCH("NF",E55,1)),"NÃO","SIM") | O55: =IF($B55=5,"SIM","") | P55: =A55&B55&C55&E55&G55&EDATE(J55,0) | Q55: =IF(A55=0,"",VLOOKUP($A55,RESUMO!$A$8:$B$83,2,FALSE))
A56: 45585 | B56: 3 | C56: 38727707000177 | D56: PASI SEGURO | E56: SEGURO COLABORADORES | G56: 155.33 | I56: 155.33 | J56: 31/10/2024 | K56: MO | N56: =IF(ISERROR(SEARCH("NF",E56,1)),"NÃO","SIM") | O56: =IF($B56=5,"SIM","") | P56: =A56&B56&C56&E56&G56&EDATE(J56,0) | Q56: =IF(A56=0,"",VLOOKUP($A56,RESUMO!$A$8:$B$83,2,FALSE))
A57: 45585 | B57: 5 | C57: 17581836000634 | D57: LOJA DO PAULO | E57: MATERIAIS DIVERSOS - NF 31532 | G57: 4268.2 | I57: 4268.2 | J57: 03/10/2024 | K57: MAT | N57: =IF(ISERROR(SEARCH("NF",E57,1)),"NÃO","SIM") | O57: =IF($B57=5,"SIM","") | P57: =A57&B57&C57&E57&G57&EDATE(J57,0) | Q57: =IF(A57=0,"",VLOOKUP($A57,RESUMO!$A$8:$B$83,2,FALSE))
A58: 45585 | B58: 5 | C58: 21543239000188 | D58: GKM COMERCIAL | E58: MATERIAIS DIVERSOS | G58: 210 | I58: 210 | J58: 03/10/2024 | K58: MAT | N58: =IF(ISERROR(SEARCH("NF",E58,1)),"NÃO","SIM") | O58: =IF($B58=5,"SIM","") | P58: =A58&B58&C58&E58&G58&EDATE(J58,0) | Q58: =IF(A58=0,"",VLOOKUP($A58,RESUMO!$A$8:$B$83,2,FALSE))
A59: 45585 | B59: 5 | C59: 07573876670 | D59: BRUNO JUNIO DA SILVA | E59: TRANSPORTE | G59: 35.8 | H59: 18 | I59: 644.4 | J59: 08/10/2024 | K59: MO | N59: =IF(ISERROR(SEARCH("NF",E59,1)),"NÃO","SIM") | O59: =IF($B59=5,"SIM","") | P59: =A59&B59&C59&E59&G59&EDATE(J59,0) | Q59: =IF(A59=0,"",VLOOKUP($A59,RESUMO!$A$8:$B$83,2,FALSE))
A60: 45585 | B60: 5 | C60: 00354432605 | D60: ANTONIO DUTRA DE FREITAS | E60: TRANSPORTE | G60: 35.8 | H60: 18 | I60: 644.4 | J60: 08/10/2024 | K60: MO | N60: =IF(ISERROR(SEARCH("NF",E60,1)),"NÃO","SIM") | O60: =IF($B60=5,"SIM","") | P60: =A60&B60&C60&E60&G60&EDATE(J60,0) | Q60: =IF(A60=0,"",VLOOKUP($A60,RESUMO!$A$8:$B$83,2,FALSE))
A61: 45585 | B61: 5 | C61: 07249031600 | D61: EDER PEREIRA DA SILVA | E61: TRANSPORTE | G61: 35.8 | H61: 18 | I61: 644.4 | J61: 08/10/2024 | K61: MO | N61: =IF(ISERROR(SEARCH("NF",E61,1)),"NÃO","SIM") | O61: =IF($B61=5,"SIM","") | P61: =A61&B61&C61&E61&G61&EDATE(J61,0) | Q61: =IF(A61=0,"",VLOOKUP($A61,RESUMO!$A$8:$B$83,2,FALSE))
A62: 45585 | B62: 5 | C62: 14758063613 | D62: IZAEL BISPO OLIVEIRA | E62: TRANSPORTE | G62: 34.5 | H62: 18 | I62: 621 | J62: 08/10/2024 | K62: MO | N62: =IF(ISERROR(SEARCH("NF",E62,1)),"NÃO","SIM") | O62: =IF($B62=5,"SIM","") | P62: =A62&B62&C62&E62&G62&EDATE(J62,0) | Q62: =IF(A62=0,"",VLOOKUP($A62,RESUMO!$A$8:$B$83,2,FALSE))
A63: 45585 | B63: 5 | C63: 85086894387 | D63: ROBEVAL PORTACIO DOS SANTOS | E63: TRANSPORTE | G63: 35.8 | H63: 18 | I63: 644.4 | J63: 08/10/2024 | K63: MO | N63: =IF(ISERROR(SEARCH("NF",E63,1)),"NÃO","SIM") | O63: =IF($B63=5,"SIM","") | P63: =A63&B63&C63&E63&G63&EDATE(J63,0) | Q63: =IF(A63=0,"",VLOOKUP($A63,RESUMO!$A$8:$B$83,2,FALSE))
A64: 45585 | B64: 5 | C64: 87942119653 | D64: DOMINGOS DA SILVA LIMA | E64: TRANSPORTE | G64: 35.8 | H64: 18 | I64: 644.4 | J64: 08/10/2024 | K64: MO | N64: =IF(ISERROR(SEARCH("NF",E64,1)),"NÃO","SIM") | O64: =IF($B64=5,"SIM","") | P64: =A64&B64&C64&E64&G64&EDATE(J64,0) | Q64: =IF(A64=0,"",VLOOKUP($A64,RESUMO!$A$8:$B$83,2,FALSE))
A65: 45585 | B65: 5 | C65: 75746980315 | D65: FRANCISCO REGO DA SILVA | E65: TRANSPORTE | G65: 35.8 | H65: 18 | I65: 644.4 | J65: 08/10/2024 | K65: MO | N65: =IF(ISERROR(SEARCH("NF",E65,1)),"NÃO","SIM") | O65: =IF($B65=5,"SIM","") | P65: =A65&B65&C65&E65&G65&EDATE(J65,0) | Q65: =IF(A65=0,"",VLOOKUP($A65,RESUMO!$A$8:$B$83,2,FALSE))
A66: 45585 | B66: 5 | C66: 07573876670 | D66: BRUNO JUNIO DA SILVA | E66: CAFÉ | G66: 4 | H66: 18 | I66: 72 | J66: 08/10/2024 | K66: MO | N66: =IF(ISERROR(SEARCH("NF",E66,1)),"NÃO","SIM") | O66: =IF($B66=5,"SIM","") | P66: =A66&B66&C66&E66&G66&EDATE(J66,0) | Q66: =IF(A66=0,"",VLOOKUP($A66,RESUMO!$A$8:$B$83,2,FALSE))
A67: 45585 | B67: 5 | C67: 00354432605 | D67: ANTONIO DUTRA DE FREITAS | E67: CAFÉ | G67: 4 | H67: 18 | I67: 72 | J67: 08/10/2024 | K67: MO | N67: =IF(ISERROR(SEARCH("NF",E67,1)),"NÃO","SIM") | O67: =IF($B67=5,"SIM","") | P67: =A67&B67&C67&E67&G67&EDATE(J67,0) | Q67: =IF(A67=0,"",VLOOKUP($A67,RESUMO!$A$8:$B$83,2,FALSE))
A68: 45585 | B68: 5 | C68: 07249031600 | D68: EDER PEREIRA DA SILVA | E68: CAFÉ | G68: 4 | H68: 18 | I68: 72 | J68: 08/10/2024 | K68: MO | N68: =IF(ISERROR(SEARCH("NF",E68,1)),"NÃO","SIM") | O68: =IF($B68=5,"SIM","") | P68: =A68&B68&C68&E68&G68&EDATE(J68,0) | Q68: =IF(A68=0,"",VLOOKUP($A68,RESUMO!$A$8:$B$83,2,FALSE))
A69: 45585 | B69: 5 | C69: 14758063613 | D69: IZAEL BISPO OLIVEIRA | E69: CAFÉ | G69: 4 | H69: 18 | I69: 72 | J69: 08/10/2024 | K69: MO | N69: =IF(ISERROR(SEARCH("NF",E69,1)),"NÃO","SIM") | O69: =IF($B69=5,"SIM","") | P69: =A69&B69&C69&E69&G69&EDATE(J69,0) | Q69: =IF(A69=0,"",VLOOKUP($A69,RESUMO!$A$8:$B$83,2,FALSE))
A70: 45585 | B70: 5 | C70: 85086894387 | D70: ROBEVAL PORTACIO DOS SANTOS | E70: CAFÉ | G70: 4 | H70: 18 | I70: 72 | J70: 08/10/2024 | K70: MO | N70: =IF(ISERROR(SEARCH("NF",E70,1)),"NÃO","SIM") | O70: =IF($B70=5,"SIM","") | P70: =A70&B70&C70&E70&G70&EDATE(J70,0) | Q70: =IF(A70=0,"",VLOOKUP($A70,RESUMO!$A$8:$B$83,2,FALSE))
... A72: 45585 | B72: 5 | C72: 75746980315 | D72: FRANCISCO REGO DA SILVA | E72: CAFÉ | G72: 4 | H72: 18 | I72: 72 | J72: 08/10/2024 | K72: MO | N72: =IF(ISERROR(SEARCH("NF",E72,1)),"NÃO","SIM") | O72: =IF($B72=5,"SIM","") | P72: =A72&B72&C72&E72&G72&EDATE(J72,0) | Q72: =IF(A72=0,"",VLOOKUP($A72,RESUMO!$A$8:$B$83,2,FALSE))
A73: 45585 | B73: 5 | C73: 21543239000188 | D73: GKM COMERCIAL | E73: ARRUELA, PORCA, BARRA | G73: 157 | I73: 157 | J73: 09/10/2024 | K73: MAT | N73: =IF(ISERROR(SEARCH("NF",E73,1)),"NÃO","SIM") | O73: =IF($B73=5,"SIM","") | P73: =A73&B73&C73&E73&G73&EDATE(J73,0) | Q73: =IF(A73=0,"",VLOOKUP($A73,RESUMO!$A$8:$B$83,2,FALSE))
A74: 45585 | B74: 5 | C74: 44611590000164 | D74: C3 TECNOLOGIA | E74: RELOGIO E CHAPEIRA DE PONTO - NF 4204 | G74: 694 | I74: 694 | J74: 10/10/2024 | K74: MAT | N74: =IF(ISERROR(SEARCH("NF",E74,1)),"NÃO","SIM") | O74: =IF($B74=5,"SIM","") | P74: =A74&B74&C74&E74&G74&EDATE(J74,0) | Q74: =IF(A74=0,"",VLOOKUP($A74,RESUMO!$A$8:$B$83,2,FALSE))
A75: 45585 | B75: 5 | C75: 07861005000158 | D75: MADECLARA COMERCIO DE MADEIRAS LTDA | E75: TABUA E ESCORA - AGUARDANDO NF | G75: 4300 | I75: 4300 | J75: 14/10/2024 | K75: MAT | N75: =IF(ISERROR(SEARCH("NF",E75,1)),"NÃO","SIM") | O75: =IF($B75=5,"SIM","") | P75: =A75&B75&C75&E75&G75&EDATE(J75,0) | Q75: =IF(A75=0,"",VLOOKUP($A75,RESUMO!$A$8:$B$83,2,FALSE))
A76: 45585 | B76: 5 | C76: 21543239000188 | D76: GKM COMERCIAL | E76: MATERIAIS DIVERSOS | G76: 553.6 | I76: 553.6 | J76: 20/09/2024 | K76: MAT | N76: =IF(ISERROR(SEARCH("NF",E76,1)),"NÃO","SIM") | O76: =IF($B76=5,"SIM","") | P76: =A76&B76&C76&E76&G76&EDATE(J76,0) | Q76: =IF(A76=0,"",VLOOKUP($A76,RESUMO!$A$8:$B$83,2,FALSE))
A77: 45585 | B77: 7 | C77: 30104762000107 | D77: VASCONCELOS & RINALDI ENGENHARIA | E77: ADM 13% - NF A EMITIR | G77: 6773.8 | I77: 6773.8 | J77: 18/10/2024 | K77: ADM | L77: PIX: 30104762000107 | N77: =IF(ISERROR(SEARCH("NF",E77,1)),"NÃO","SIM") | O77: =IF($B77=5,"SIM","") | P77: =A77&B77&C77&E77&G77&EDATE(J77,0) | Q77: =IF(A77=0,"",VLOOKUP($A77,RESUMO!$A$8:$B$83,2,FALSE))
A78: 45601 | B78: 1 | C78: 07573876670 | D78: BRUNO JUNIO DA SILVA | E78: SALÁRIO | G78: 2193.04 | I78: 2193.04 | J78: 06/11/2024 | K78: MO | L78: PIX: 07573876670 | N78: =IF(ISERROR(SEARCH("NF",E78,1)),"NÃO","SIM") | O78: =IF($B78=5,"SIM","") | P78: =A78&B78&C78&E78&G78&EDATE(J78,0) | Q78: =IF(A78=0,"",VLOOKUP($A78,RESUMO!$A$8:$B$83,2,FALSE))
A79: 45601 | B79: 1 | C79: 00354432605 | D79: ANTONIO DUTRA DE FREITAS | E79: SALÁRIO | G79: 1148.08 | I79: 1148.08 | J79: 06/11/2024 | K79: MO | L79: PIX: 31982618378 | N79: =IF(ISERROR(SEARCH("NF",E79,1)),"NÃO","SIM") | O79: =IF($B79=5,"SIM","") | P79: =A79&B79&C79&E79&G79&EDATE(J79,0) | Q79: =IF(A79=0,"",VLOOKUP($A79,RESUMO!$A$8:$B$83,2,FALSE))
A80: 45601 | B80: 1 | C80: 07249031600 | D80: EDER PEREIRA DA SILVA | E80: SALÁRIO | G80: 1148.08 | I80: 1148.08 | J80: 06/11/2024 | K80: MO | L80: PIX: 07249031600 | N80: =IF(ISERROR(SEARCH("NF",E80,1)),"NÃO","SIM") | O80: =IF($B80=5,"SIM","") | P80: =A80&B80&C80&E80&G80&EDATE(J80,0) | Q80: =IF(A80=0,"",VLOOKUP($A80,RESUMO!$A$8:$B$83,2,FALSE))
A81: 45601 | B81: 1 | C81: 14758063613 | D81: IZAEL BISPO OLIVEIRA | E81: SALÁRIO | G81: 1148.08 | I81: 1148.08 | J81: 06/11/2024 | K81: MO | L81: PIX: 14758063613 | N81: =IF(ISERROR(SEARCH("NF",E81,1)),"NÃO","SIM") | O81: =IF($B81=5,"SIM","") | P81: =A81&B81&C81&E81&G81&EDATE(J81,0) | Q81: =IF(A81=0,"",VLOOKUP($A81,RESUMO!$A$8:$B$83,2,FALSE))
A82: 45601 | B82: 1 | C82: 85086894387 | D82: ROBEVAL PORTACIO DOS SANTOS | E82: SALÁRIO | G82: 674.94 | I82: 674.94 | J82: 06/11/2024 | K82: MO | L82: PIX: 31971706400 | N82: =IF(ISERROR(SEARCH("NF",E82,1)),"NÃO","SIM") | O82: =IF($B82=5,"SIM","") | P82: =A82&B82&C82&E82&G82&EDATE(J82,0) | Q82: =IF(A82=0,"",VLOOKUP($A82,RESUMO!$A$8:$B$83,2,FALSE))
A83: 45601 | B83: 1 | C83: 87942119653 | D83: DOMINGOS DA SILVA LIMA | E83: SALÁRIO | G83: 674.94 | I83: 674.94 | J83: 06/11/2024 | K83: MO | L83: CEF 013 0892 00113057-1 - CPF: 87.942.119.6-53 | N83: =IF(ISERROR(SEARCH("NF",E83,1)),"NÃO","SIM") | O83: =IF($B83=5,"SIM","") | P83: =A83&B83&C83&E83&G83&EDATE(J83,0) | Q83: =IF(A83=0,"",VLOOKUP($A83,RESUMO!$A$8:$B$83,2,FALSE))
A84: 45601 | B84: 1 | C84: 75746980315 | D84: FRANCISCO REGO DA SILVA | E84: SALÁRIO | G84: 955.5 | I84: 955.5 | J84: 06/11/2024 | K84: MO | L84: PIX: 75746980315 | N84: =IF(ISERROR(SEARCH("NF",E84,1)),"NÃO","SIM") | O84: =IF($B84=5,"SIM","") | P84: =A84&B84&C84&E84&G84&EDATE(J84,0) | Q84: =IF(A84=0,"",VLOOKUP($A84,RESUMO!$A$8:$B$83,2,FALSE))
A85: 45601 | B85: 1 | C85: 07573876670 | D85: BRUNO JUNIO DA SILVA | E85: TRANSPORTE | G85: 40.8 | H85: 19 | I85: 775.2 | J85: 06/11/2024 | K85: MO | L85: PIX: 07573876670 | N85: =IF(ISERROR(SEARCH("NF",E85,1)),"NÃO","SIM") | O85: =IF($B85=5,"SIM","") | P85: =A85&B85&C85&E85&G85&EDATE(J85,0) | Q85: =IF(A85=0,"",VLOOKUP($A85,RESUMO!$A$8:$B$83,2,FALSE))
A86: 45601 | B86: 1 | C86: 00354432605 | D86: ANTONIO DUTRA DE FREITAS | E86: TRANSPORTE | G86: 40.8 | H86: 19 | I86: 775.2 | J86: 06/11/2024 | K86: MO | L86: PIX: 31982618378 | N86: =IF(ISERROR(SEARCH("NF",E86,1)),"NÃO","SIM") | O86: =IF($B86=5,"SIM","") | P86: =A86&B86&C86&E86&G86&EDATE(J86,0) | Q86: =IF(A86=0,"",VLOOKUP($A86,RESUMO!$A$8:$B$83,2,FALSE))
A87: 45601 | B87: 1 | C87: 07249031600 | D87: EDER PEREIRA DA SILVA | E87: TRANSPORTE | G87: 40.8 | H87: 19 | I87: 775.2 | J87: 06/11/2024 | K87: MO | L87: PIX: 07249031600 | N87: =IF(ISERROR(SEARCH("NF",E87,1)),"NÃO","SIM") | O87: =IF($B87=5,"SIM","") | P87: =A87&B87&C87&E87&G87&EDATE(J87,0) | Q87: =IF(A87=0,"",VLOOKUP($A87,RESUMO!$A$8:$B$83,2,FALSE))
A88: 45601 | B88: 1 | C88: 14758063613 | D88: IZAEL BISPO OLIVEIRA | E88: TRANSPORTE | G88: 42.3 | H88: 19 | I88: 803.7 | J88: 06/11/2024 | K88: MO | L88: PIX: 14758063613 | N88: =IF(ISERROR(SEARCH("NF",E88,1)),"NÃO","SIM") | O88: =IF($B88=5,"SIM","") | P88: =A88&B88&C88&E88&G88&EDATE(J88,0) | Q88: =IF(A88=0,"",VLOOKUP($A88,RESUMO!$A$8:$B$83,2,FALSE))
A89: 45601 | B89: 1 | C89: 85086894387 | D89: ROBEVAL PORTACIO DOS SANTOS | E89: TRANSPORTE | G89: 40.8 | H89: 19 | I89: 775.2 | J89: 06/11/2024 | K89: MO | L89: PIX: 31971706400 | N89: =IF(ISERROR(SEARCH("NF",E89,1)),"NÃO","SIM") | O89: =IF($B89=5,"SIM","") | P89: =A89&B89&C89&E89&G89&EDATE(J89,0) | Q89: =IF(A89=0,"",VLOOKUP($A89,RESUMO!$A$8:$B$83,2,FALSE))
A90: 45601 | B90: 1 | C90: 87942119653 | D90: DOMINGOS DA SILVA LIMA | E90: TRANSPORTE | G90: 40.8 | H90: 19 | I90: 775.2 | J90: 06/11/2024 | K90: MO | L90: CEF 013 0892 00113057-1 - CPF: 87.942.119.6-53 | N90: =IF(ISERROR(SEARCH("NF",E90,1)),"NÃO","SIM") | O90: =IF($B90=5,"SIM","") | P90: =A90&B90&C90&E90&G90&EDATE(J90,0) | Q90: =IF(A90=0,"",VLOOKUP($A90,RESUMO!$A$8:$B$83,2,FALSE))
A91: 45601 | B91: 1 | C91: 75746980315 | D91: FRANCISCO REGO DA SILVA | E91: TRANSPORTE | G91: 40.8 | H91: 19 | I91: 775.2 | J91: 06/11/2024 | K91: MO | L91: PIX: 75746980315 | N91: =IF(ISERROR(SEARCH("NF",E91,1)),"NÃO","SIM") | O91: =IF($B91=5,"SIM","") | P91: =A91&B91&C91&E91&G91&EDATE(J91,0) | Q91: =IF(A91=0,"",VLOOKUP($A91,RESUMO!$A$8:$B$83,2,FALSE))
A92: 45601 | B92: 1 | C92: 07573876670 | D92: BRUNO JUNIO DA SILVA | E92: CAFÉ | G92: 4 | H92: 19 | I92: 76 | J92: 06/11/2024 | K92: MO | L92: PIX: 07573876670 | N92: =IF(ISERROR(SEARCH("NF",E92,1)),"NÃO","SIM") | O92: =IF($B92=5,"SIM","") | P92: =A92&B92&C92&E92&G92&EDATE(J92,0) | Q92: =IF(A92=0,"",VLOOKUP($A92,RESUMO!$A$8:$B$83,2,FALSE))
A93: 45601 | B93: 1 | C93: 00354432605 | D93: ANTONIO DUTRA DE FREITAS | E93: CAFÉ | G93: 4 | H93: 19 | I93: 76 | J93: 06/11/2024 | K93: MO | L93: PIX: 31982618378 | N93: =IF(ISERROR(SEARCH("NF",E93,1)),"NÃO","SIM") | O93: =IF($B93=5,"SIM","") | P93: =A93&B93&C93&E93&G93&EDATE(J93,0) | Q93: =IF(A93=0,"",VLOOKUP($A93,RESUMO!$A$8:$B$83,2,FALSE))
A94: 45601 | B94: 1 | C94: 07249031600 | D94: EDER PEREIRA DA SILVA | E94: CAFÉ | G94: 4 | H94: 19 | I94: 76 | J94: 06/11/2024 | K94: MO | L94: PIX: 07249031600 | N94: =IF(ISERROR(SEARCH("NF",E94,1)),"NÃO","SIM") | O94: =IF($B94=5,"SIM","") | P94: =A94&B94&C94&E94&G94&EDATE(J94,0) | Q94: =IF(A94=0,"",VLOOKUP($A94,RESUMO!$A$8:$B$83,2,FALSE))
A95: 45601 | B95: 1 | C95: 14758063613 | D95: IZAEL BISPO OLIVEIRA | E95: CAFÉ | G95: 4 | H95: 19 | I95: 76 | J95: 06/11/2024 | K95: MO | L95: PIX: 14758063613 | N95: =IF(ISERROR(SEARCH("NF",E95,1)),"NÃO","SIM") | O95: =IF($B95=5,"SIM","") | P95: =A95&B95&C95&E95&G95&EDATE(J95,0) | Q95: =IF(A95=0,"",VLOOKUP($A95,RESUMO!$A$8:$B$83,2,FALSE))
A96: 45601 | B96: 1 | C96: 85086894387 | D96: ROBEVAL PORTACIO DOS SANTOS | E96: CAFÉ | G96: 4 | H96: 19 | I96: 76 | J96: 06/11/2024 | K96: MO | L96: PIX: 31971706400 | N96: =IF(ISERROR(SEARCH("NF",E96,1)),"NÃO","SIM") | O96: =IF($B96=5,"SIM","") | P96: =A96&B96&C96&E96&G96&EDATE(J96,0) | Q96: =IF(A96=0,"",VLOOKUP($A96,RESUMO!$A$8:$B$83,2,FALSE))
... A99: 45601 | B99: 1 | C99: 36404993600 | D99: NIVALDO DA SILVA | E99: DIÁRIA | G99: 270 | H99: 3 | I99: 810 | J99: 07/11/2024 | K99: MO | L99: PIX: 36404993600 | N99: =IF(ISERROR(SEARCH("NF",E99,1)),"NÃO","SIM") | O99: =IF($B99=5,"SIM","") | P99: =A99&B99&C99&E99&G99&EDATE(J99,0) | Q99: =IF(A99=0,"",VLOOKUP($A99,RESUMO!$A$8:$B$83,2,FALSE))
A100: 45601 | B100: 2 | C100: 00000011126 | D100: MHS MENSALIDADE | E100: COMPETENCIA 10/2024 | G100: 704 | I100: 704 | J100: 06/11/2024 | K100: MO | L100: PIX: 31995901635 | N100: =IF(ISERROR(SEARCH("NF",E100,1)),"NÃO","SIM") | O100: =IF($B100=5,"SIM","") | P100: =A100&B100&C100&E100&G100&EDATE(J100,0) | Q100: =IF(A100=0,"",VLOOKUP($A100,RESUMO!$A$8:$B$83,2,FALSE))
A101: 45601 | B101: 2 | C101: 00000011207 | D101: MOTOBOY | E101: COMPETENCIA 10/2024 | G101: 135 | I101: 135 | J101: 06/11/2024 | K101: DIV | L101: PIX: 31995901635 | N101: =IF(ISERROR(SEARCH("NF",E101,1)),"NÃO","SIM") | O101: =IF($B101=5,"SIM","") | P101: =A101&B101&C101&E101&G101&EDATE(J101,0) | Q101: =IF(A101=0,"",VLOOKUP($A101,RESUMO!$A$8:$B$83,2,FALSE))
A102: 45601 | B102: 2 | C102: 00000011398 | D102: FOLHA DP | E102: COMPETENCIA 10/2024 | G102: 847.2 | I102: 847.2 | J102: 06/11/2024 | K102: MO | L102: PIX: 31995901635 | N102: =IF(ISERROR(SEARCH("NF",E102,1)),"NÃO","SIM") | O102: =IF($B102=5,"SIM","") | P102: =A102&B102&C102&E102&G102&EDATE(J102,0) | Q102: =IF(A102=0,"",VLOOKUP($A102,RESUMO!$A$8:$B$83,2,FALSE))
A103: 45601 | B103: 2 | C103: 07834753000141 | D103: ANCORA PAPELARIA | E103: PLOTAGENS - NF A EMITIR | G103: 226.5 | I103: 226.5 | J103: 06/11/2024 | K103: SERV | L103: PIX: ancorapapelaria@gmail.com | N103: =IF(ISERROR(SEARCH("NF",E103,1)),"NÃO","SIM") | O103: =IF($B103=5,"SIM","") | P103: =A103&B103&C103&E103&G103&EDATE(J103,0) | Q103: =IF(A103=0,"",VLOOKUP($A103,RESUMO!$A$8:$B$83,2,FALSE))
...

Sheet RESUMO
G1: Rua Zodiaco, 87 Sala 07 – Santa Lúcia - Belo Horizonte - MG (31) 3654-6616 / (31) 99974-1241 / (31) 98711-1139 rvr.engenharia@gmail.com / vinicius.rinaldi26@gmail.com
A3: CLEVER LUIZ SALVADOR | K3: Data Inicial: | L3: 45540
A4: RUA MARES DE MONTANHAS, 465 - CONDOMINIO VALE DOS CRISTAIS | K4: % Adm Obra: | L4: 0.13
A6: RESUMO DAS DESPESAS | N6: % ADM OBRA
C7: 1 | D7: 2 | E7: 3 | F7: 4 | G7: 5 | H7: 6
A8: DATA | B8: Nº REL. | C8: 1) DESPESAS COM COLABORADORES | D8: 2) TRANSF. PROGR. - MATERIAIS, LOCAÇÕES E PREST. SERVIÇOS | E8: 3) MATERIAIS, PREST DE SERVIÇOS, IMPOSTOS E OUTROS | F8: 4) RESSARCIMENTOS E RESTITUIÇÕES | G8: 5) DESPESAS PAGAS PELO CLIENTE | H8: 6) PAGAMENTOS CAIXA DE OBRA | I8: SUBTOTAL | J8: 7) ADM. OBRA | K8: TOTAL | L8: ACUMULADO
A9: 45540 | B9: 1 | C9: =SUMIFS(Dados!$I$1:$I$1910,Dados!$B$1:$B$1910,C$7,Dados!$A$1:$A$1910,$A9) | D9: =SUMIFS(Dados!$I$1:$I$1910,Dados!$B$1:$B$1910,D$7,Dados!$A$1:$A$1910,$A9) | E9: =SUMIFS(Dados!$I$1:$I$1910,Dados!$B$1:$B$1910,E$7,Dados!$A$1:$A$1910,$A9) | F9: =SUMIFS(Dados!$I$1:$I$1910,Dados!$B$1:$B$1910,F$7,Dados!$A$1:$A$1910,$A9) | G9: =SUMIFS(Dados!$I$1:$I$1910,Dados!$B$1:$B$1910,G$7,Dados!$A$1:$A$1910,$A9) | H9: =SUMIFS(Dados!$I$1:$I$1910,Dados!$B$1:$B$1910,H$7,Dados!$A$1:$A$1910,$A9) | I9: =SUM(C9:H9) | J9: =ROUND(I9*$L$4,2) | K9: =SUM(I9:J9) | L9: =K9
A10: 45555 | B10: =B9+1 | C10: =SUMIFS(Dados!$I$1:$I$1910,Dados!$B$1:$B$1910,C$7,Dados!$A$1:$A$1910,$A10) | D10: =SUMIFS(Dados!$I$1:$I$1910,Dados!$B$1:$B$1910,D$7,Dados!$A$1:$A$1910,$A10) | E10: =SUMIFS(Dados!$I$1:$I$1910,Dados!$B$1:$B$1910,E$7,Dados!$A$1:$A$1910,$A10) | F10: =SUMIFS(Dados!$I$1:$I$1910,Dados!$B$1:$B$1910,F$7,Dados!$A$1:$A$1910,$A10) | G10: =SUMIFS(Dados!$I$1:$I$1910,Dados!$B$1:$B$1910,G$7,Dados!$A$1:$A$1910,$A10) | H10: =SUMIFS(Dados!$I$1:$I$1910,Dados!$B$1:$B$1910,H$7,Dados!$A$1:$A$1910,$A10) | I10: =SUM(C10:H10) | J10: =ROUND(I10*$L$4,2) | K10: =SUM(I10:J10) | L10: =ROUND(K10+L9,2)
A11: 45570 | B11: =B10+1 | C11: =SUMIFS(Dados!$I$1:$I$1910,Dados!$B$1:$B$1910,C$7,Dados!$A$1:$A$1910,$A11) | D11: =SUMIFS(Dados!$I$1:$I$1910,Dados!$B$1:$B$1910,D$7,Dados!$A$1:$A$1910,$A11) | E11: =SUMIFS(Dados!$I$1:$I$1910,Dados!$B$1:$B$1910,E$7,Dados!$A$1:$A$1910,$A11) | F11: =SUMIFS(Dados!$I$1:$I$1910,Dados!$B$1:$B$1910,F$7,Dados!$A$1:$A$1910,$A11) | G11: =SUMIFS(Dados!$I$1:$I$1910,Dados!$B$1:$B$1910,G$7,Dados!$A$1:$A$1910,$A11) | H11: =SUMIFS(Dados!$I$1:$I$1910,Dados!$B$1:$B$1910,H$7,Dados!$A$1:$A$1910,$A11) | I11: =SUM(C11:H11) | J11: =ROUND(I11*$L$4,2) | K11: =SUM(I11:J11) | L11: =ROUND(K11+L10,2)
A12: 45585 | B12: =B11+1 | C12: =SUMIFS(Dados!$I$1:$I$1910,Dados!$B$1:$B$1910,C$7,Dados!$A$1:$A$1910,$A12) | D12: =SUMIFS(Dados!$I$1:$I$1910,Dados!$B$1:$B$1910,D$7,Dados!$A$1:$A$1910,$A12) | E12: =SUMIFS(Dados!$I$1:$I$1910,Dados!$B$1:$B$1910,E$7,Dados!$A$1:$A$1910,$A12) | F12: =SUMIFS(Dados!$I$1:$I$1910,Dados!$B$1:$B$1910,F$7,Dados!$A$1:$A$1910,$A12) | G12: =SUMIFS(Dados!$I$1:$I$1910,Dados!$B$1:$B$1910,G$7,Dados!$A$1:$A$1910,$A12) | H12: =SUMIFS(Dados!$I$1:$I$1910,Dados!$B$1:$B$1910,H$7,Dados!$A$1:$A$1910,$A12) | I12: =SUM(C12:H12) | J12: =ROUND(I12*$L$4,2) | K12: =SUM(I12:J12) | L12: =ROUND(K12+L11,2)
A13: 45601 | B13: =B12+1 | C13: =SUMIFS(Dados!$I$1:$I$1910,Dados!$B$1:$B$1910,C$7,Dados!$A$1:$A$1910,$A13) | D13: =SUMIFS(Dados!$I$1:$I$1910,Dados!$B$1:$B$1910,D$7,Dados!$A$1:$A$1910,$A13) | E13: =SUMIFS(Dados!$I$1:$I$1910,Dados!$B$1:$B$1910,E$7,Dados!$A$1:$A$1910,$A13) | F13: =SUMIFS(Dados!$I$1:$I$1910,Dados!$B$1:$B$1910,F$7,Dados!$A$1:$A$1910,$A13) | G13: =SUMIFS(Dados!$I$1:$I$1910,Dados!$B$1:$B$1910,G$7,Dados!$A$1:$A$1910,$A13) | H13: =SUMIFS(Dados!$I$1:$I$1910,Dados!$B$1:$B$1910,H$7,Dados!$A$1:$A$1910,$A13) | I13: =SUM(C13:H13) | J13: =ROUND(I13*$L$4,2) | K13: =SUM(I13:J13) | L13: =ROUND(K13+L12,2)
A14: 45616 | B14: =B13+1 | C14: =SUMIFS(Dados!$I$1:$I$1910,Dados!$B$1:$B$1910,C$7,Dados!$A$1:$A$1910,$A14) | D14: =SUMIFS(Dados!$I$1:$I$1910,Dados!$B$1:$B$1910,D$7,Dados!$A$1:$A$1910,$A14) | E14: =SUMIFS(Dados!$I$1:$I$1910,Dados!$B$1:$B$1910,E$7,Dados!$A$1:$A$1910,$A14) | F14: =SUMIFS(Dados!$I$1:$I$1910,Dados!$B$1:$B$1910,F$7,Dados!$A$1:$A$1910,$A14) | G14: =SUMIFS(Dados!$I$1:$I$1910,Dados!$B$1:$B$1910,G$7,Dados!$A$1:$A$1910,$A14) | H14: =SUMIFS(Dados!$I$1:$I$1910,Dados!$B$1:$B$1910,H$7,Dados!$A$1:$A$1910,$A14) | I14: =SUM(C14:H14) | J14: =ROUND(I14*$L$4,2) | K14: =SUM(I14:J14) | L14: =ROUND(K14+L13,2)
A15: 45631 | B15: =B14+1 | C15: =SUMIFS(Dados!$I$1:$I$1910,Dados!$B$1:$B$1910,C$7,Dados!$A$1:$A$1910,$A15) | D15: =SUMIFS(Dados!$I$1:$I$1910,Dados!$B$1:$B$1910,D$7,Dados!$A$1:$A$1910,$A15) | E15: =SUMIFS(Dados!$I$1:$I$1910,Dados!$B$1:$B$1910,E$7,Dados!$A$1:$A$1910,$A15) | F15: =SUMIFS(Dados!$I$1:$I$1910,Dados!$B$1:$B$1910,F$7,Dados!$A$1:$A$1910,$A15) | G15: =SUMIFS(Dados!$I$1:$I$1910,Dados!$B$1:$B$1910,G$7,Dados!$A$1:$A$1910,$A15) | H15: =SUMIFS(Dados!$I$1:$I$1910,Dados!$B$1:$B$1910,H$7,Dados!$A$1:$A$1910,$A15) | I15: =SUM(C15:H15) | J15: =ROUND(I15*$L$4,2) | K15: =SUM(I15:J15) | L15: =ROUND(K15+L14,2)
A16: 45646 | B16: =B15+1 | C16: =SUMIFS(Dados!$I$1:$I$1910,Dados!$B$1:$B$1910,C$7,Dados!$A$1:$A$1910,$A16) | D16: =SUMIFS(Dados!$I$1:$I$1910,Dados!$B$1:$B$1910,D$7,Dados!$A$1:$A$1910,$A16) | E16: =SUMIFS(Dados!$I$1:$I$1910,Dados!$B$1:$B$1910,E$7,Dados!$A$1:$A$1910,$A16) | F16: =SUMIFS(Dados!$I$1:$I$1910,Dados!$B$1:$B$1910,F$7,Dados!$A$1:$A$1910,$A16) | G16: =SUMIFS(Dados!$I$1:$I$1910,Dados!$B$1:$B$1910,G$7,Dados!$A$1:$A$1910,$A16) | H16: =SUMIFS(Dados!$I$1:$I$1910,Dados!$B$1:$B$1910,H$7,Dados!$A$1:$A$1910,$A16) | I16: =SUM(C16:H16) | J16: =ROUND(I16*$L$4,2) | K16: =SUM(I16:J16) | L16: =ROUND(K16+L15,2)
A17: 45662 | B17: =B16+1 | C17: =SUMIFS(Dados!$I$1:$I$1910,Dados!$B$1:$B$1910,C$7,Dados!$A$1:$A$1910,$A17) | D17: =SUMIFS(Dados!$I$1:$I$1910,Dados!$B$1:$B$1910,D$7,Dados!$A$1:$A$1910,$A17) | E17: =SUMIFS(Dados!$I$1:$I$1910,Dados!$B$1:$B$1910,E$7,Dados!$A$1:$A$1910,$A17) | F17: =SUMIFS(Dados!$I$1:$I$1910,Dados!$B$1:$B$1910,F$7,Dados!$A$1:$A$1910,$A17) | G17: =SUMIFS(Dados!$I$1:$I$1910,Dados!$B$1:$B$1910,G$7,Dados!$A$1:$A$1910,$A17) | H17: =SUMIFS(Dados!$I$1:$I$1910,Dados!$B$1:$B$1910,H$7,Dados!$A$1:$A$1910,$A17) | I17: =SUM(C17:H17) | J17: =ROUND(I17*$L$4,2) | K17: =SUM(I17:J17) | L17: =ROUND(K17+L16,2)
A18: 45677 | B18: =B17+1 | C18: =SUMIFS(Dados!$I$1:$I$1910,Dados!$B$1:$B$1910,C$7,Dados!$A$1:$A$1910,$A18) | D18: =SUMIFS(Dados!$I$1:$I$1910,Dados!$B$1:$B$1910,D$7,Dados!$A$1:$A$1910,$A18) | E18: =SUMIFS(Dados!$I$1:$I$1910,Dados!$B$1:$B$1910,E$7,Dados!$A$1:$A$1910,$A18) | F18: =SUMIFS(Dados!$I$1:$I$1910,Dados!$B$1:$B$1910,F$7,Dados!$A$1:$A$1910,$A18) | G18: =SUMIFS(Dados!$I$1:$I$1910,Dados!$B$1:$B$1910,G$7,Dados!$A$1:$A$1910,$A18) | H18: =SUMIFS(Dados!$I$1:$I$1910,Dados!$B$1:$B$1910,H$7,Dados!$A$1:$A$1910,$A18) | I18: =SUM(C18:H18) | J18: =ROUND(I18*$L$4,2) | K18: =SUM(I18:J18) | L18: =ROUND(K18+L17,2)
A19: 45693 | B19: =B18+1 | C19: =SUMIFS(Dados!$I$1:$I$1910,Dados!$B$1:$B$1910,C$7,Dados!$A$1:$A$1910,$A19) | D19: =SUMIFS(Dados!$I$1:$I$1910,Dados!$B$1:$B$1910,D$7,Dados!$A$1:$A$1910,$A19) | E19: =SUMIFS(Dados!$I$1:$I$1910,Dados!$B$1:$B$1910,E$7,Dados!$A$1:$A$1910,$A19) | F19: =SUMIFS(Dados!$I$1:$I$1910,Dados!$B$1:$B$1910,F$7,Dados!$A$1:$A$1910,$A19) | G19: =SUMIFS(Dados!$I$1:$I$1910,Dados!$B$1:$B$1910,G$7,Dados!$A$1:$A$1910,$A19) | H19: =SUMIFS(Dados!$I$1:$I$1910,Dados!$B$1:$B$1910,H$7,Dados!$A$1:$A$1910,$A19) | I19: =SUM(C19:H19) | J19: =ROUND(I19*$L$4,2) | K19: =SUM(I19:J19) | L19: =ROUND(K19+L18,2)
A20: 45708 | B20: =B19+1 | C20: =SUMIFS(Dados!$I$1:$I$1910,Dados!$B$1:$B$1910,C$7,Dados!$A$1:$A$1910,$A20) | D20: =SUMIFS(Dados!$I$1:$I$1910,Dados!$B$1:$B$1910,D$7,Dados!$A$1:$A$1910,$A20) | E20: =SUMIFS(Dados!$I$1:$I$1910,Dados!$B$1:$B$1910,E$7,Dados!$A$1:$A$1910,$A20) | F20: =SUMIFS(Dados!$I$1:$I$1910,Dados!$B$1:$B$1910,F$7,Dados!$A$1:$A$1910,$A20) | G20: =SUMIFS(Dados!$I$1:$I$1910,Dados!$B$1:$B$1910,G$7,Dados!$A$1:$A$1910,$A20) | H20: =SUMIFS(Dados!$I$1:$I$1910,Dados!$B$1:$B$1910,H$7,Dados!$A$1:$A$1910,$A20) | I20: =SUM(C20:H20) | J20: =ROUND(I20*$L$4,2) | K20: =SUM(I20:J20) | L20: =ROUND(K20+L19,2)
A21: 45721 | B21: =B20+1 | C21: =SUMIFS(Dados!$I$1:$I$1910,Dados!$B$1:$B$1910,C$7,Dados!$A$1:$A$1910,$A21) | D21: =SUMIFS(Dados!$I$1:$I$1910,Dados!$B$1:$B$1910,D$7,Dados!$A$1:$A$1910,$A21) | E21: =SUMIFS(Dados!$I$1:$I$1910,Dados!$B$1:$B$1910,E$7,Dados!$A$1:$A$1910,$A21) | F21: =SUMIFS(Dados!$I$1:$I$1910,Dados!$B$1:$B$1910,F$7,Dados!$A$1:$A$1910,$A21) | G21: =SUMIFS(Dados!$I$1:$I$1910,Dados!$B$1:$B$1910,G$7,Dados!$A$1:$A$1910,$A21) | H21: =SUMIFS(Dados!$I$1:$I$1910,Dados!$B$1:$B$1910,H$7,Dados!$A$1:$A$1910,$A21) | I21: =SUM(C21:H21) | J21: =ROUND(I21*$L$4,2) | K21: =SUM(I21:J21) | L21: =ROUND(K21+L20,2)
... A80: 46619 | B80: =B79+1 | C80: =SUMIFS(Dados!$I$1:$I$1910,Dados!$B$1:$B$1910,C$7,Dados!$A$1:$A$1910,$A80) | D80: =SUMIFS(Dados!$I$1:$I$1910,Dados!$B$1:$B$1910,D$7,Dados!$A$1:$A$1910,$A80) | E80: =SUMIFS(Dados!$I$1:$I$1910,Dados!$B$1:$B$1910,E$7,Dados!$A$1:$A$1910,$A80) | F80: =SUMIFS(Dados!$I$1:$I$1910,Dados!$B$1:$B$1910,F$7,Dados!$A$1:$A$1910,$A80) | G80: =SUMIFS(Dados!$I$1:$I$1910,Dados!$B$1:$B$1910,G$7,Dados!$A$1:$A$1910,$A80) | H80: =SUMIFS(Dados!$I$1:$I$1910,Dados!$B$1:$B$1910,H$7,Dados!$A$1:$A$1910,$A80) | I80: =SUM(C80:H80) | J80: =ROUND(I80*$L$4,2) | K80: =SUM(I80:J80) | L80: =ROUND(K80+L79,2)
A81: TOTAL | C81: =SUM(C9:C80) | D81: =SUM(D9:D80) | E81: =SUM(E9:E80) | F81: =SUM(F9:F80) | G81: =SUM(G9:G80) | H81: =SUM(H9:H80) | I81: =SUM(I9:I80) | J81: =SUM(J9:J80) | K81: =SUM(K9:K80)

Sheet Tp.Despesas
G1: Rua Zodiaco, 87 Sala 07 – Santa Lúcia - Belo Horizonte - MG (31) 3654-6616 / (31) 99974-1241 / (31) 98711-1139 rvr.engenharia@gmail.com / vinicius.rinaldi26@gmail.com
A3: =RESUMO!A3
A4: =RESUMO!A4
A6: RESUMO POR TIPO DE DESPESAS
C7: ADM | D7: DIV | E7: LOC | F7: MAT | G7: MO | H7: SERV | I7: TP
A8: DATA | C8: ADMINISTRATIVO | D8: DIVERSOS | E8: LOCAÇAO | F8: MATERIAL | G8: MÃO DE OBRA | H8: SERVIÇOS | I8: TARIFAS/TRIBUTOS PÚBLICAS | J8: TOTAL
A9: =DATE(YEAR(RESUMO!A9),MONTH(RESUMO!A9),1) | C9: =SUMIFS(Dados!$I$1:$I$1919,Dados!$K$1:$K$1919,Tp.Despesas!C$7,Dados!$A$1:$A$1919,">="&$A9,Dados!$A$1:$A$1919,"<="&EOMONTH($A9,0)) | D9: =SUMIFS(Dados!$I$1:$I$1919,Dados!$K$1:$K$1919,Tp.Despesas!D$7,Dados!$A$1:$A$1919,">="&$A9,Dados!$A$1:$A$1919,"<="&EOMONTH($A9,0)) | E9: =SUMIFS(Dados!$I$1:$I$1919,Dados!$K$1:$K$1919,Tp.Despesas!E$7,Dados!$A$1:$A$1919,">="&$A9,Dados!$A$1:$A$1919,"<="&EOMONTH($A9,0)) | F9: =SUMIFS(Dados!$I$1:$I$1919,Dados!$K$1:$K$1919,Tp.Despesas!F$7,Dados!$A$1:$A$1919,">="&$A9,Dados!$A$1:$A$1919,"<="&EOMONTH($A9,0)) | G9: =SUMIFS(Dados!$I$1:$I$1919,Dados!$K$1:$K$1919,Tp.Despesas!G$7,Dados!$A$1:$A$1919,">="&$A9,Dados!$A$1:$A$1919,"<="&EOMONTH($A9,0)) | H9: =SUMIFS(Dados!$I$1:$I$1919,Dados!$K$1:$K$1919,Tp.Despesas!H$7,Dados!$A$1:$A$1919,">="&$A9,Dados!$A$1:$A$1919,"<="&EOMONTH($A9,0)) | I9: =SUMIFS(Dados!$I$1:$I$1919,Dados!$K$1:$K$1919,Tp.Despesas!I$7,Dados!$A$1:$A$1919,">="&$A9,Dados!$A$1:$A$1919,"<="&EOMONTH($A9,0)) | J9: =SUM(C9:I9)
A10: =EOMONTH(A9,1)-DAY(EOMONTH(A9,1))+1 | C10: =SUMIFS(Dados!$I$1:$I$1919,Dados!$K$1:$K$1919,Tp.Despesas!C$7,Dados!$A$1:$A$1919,">="&$A10,Dados!$A$1:$A$1919,"<="&EOMONTH($A10,0)) | D10: =SUMIFS(Dados!$I$1:$I$1919,Dados!$K$1:$K$1919,Tp.Despesas!D$7,Dados!$A$1:$A$1919,">="&$A10,Dados!$A$1:$A$1919,"<="&EOMONTH($A10,0)) | E10: =SUMIFS(Dados!$I$1:$I$1919,Dados!$K$1:$K$1919,Tp.Despesas!E$7,Dados!$A$1:$A$1919,">="&$A10,Dados!$A$1:$A$1919,"<="&EOMONTH($A10,0)) | F10: =SUMIFS(Dados!$I$1:$I$1919,Dados!$K$1:$K$1919,Tp.Despesas!F$7,Dados!$A$1:$A$1919,">="&$A10,Dados!$A$1:$A$1919,"<="&EOMONTH($A10,0)) | G10: =SUMIFS(Dados!$I$1:$I$1919,Dados!$K$1:$K$1919,Tp.Despesas!G$7,Dados!$A$1:$A$1919,">="&$A10,Dados!$A$1:$A$1919,"<="&EOMONTH($A10,0)) | H10: =SUMIFS(Dados!$I$1:$I$1919,Dados!$K$1:$K$1919,Tp.Despesas!H$7,Dados!$A$1:$A$1919,">="&$A10,Dados!$A$1:$A$1919,"<="&EOMONTH($A10,0)) | I10: =SUMIFS(Dados!$I$1:$I$1919,Dados!$K$1:$K$1919,Tp.Despesas!I$7,Dados!$A$1:$A$1919,">="&$A10,Dados!$A$1:$A$1919,"<="&EOMONTH($A10,0)) | J10: =SUM(C10:I10)
A11: =EOMONTH(A10,1)-DAY(EOMONTH(A10,1))+1 | C11: =SUMIFS(Dados!$I$1:$I$1919,Dados!$K$1:$K$1919,Tp.Despesas!C$7,Dados!$A$1:$A$1919,">="&$A11,Dados!$A$1:$A$1919,"<="&EOMONTH($A11,0)) | D11: =SUMIFS(Dados!$I$1:$I$1919,Dados!$K$1:$K$1919,Tp.Despesas!D$7,Dados!$A$1:$A$1919,">="&$A11,Dados!$A$1:$A$1919,"<="&EOMONTH($A11,0)) | E11: =SUMIFS(Dados!$I$1:$I$1919,Dados!$K$1:$K$1919,Tp.Despesas!E$7,Dados!$A$1:$A$1919,">="&$A11,Dados!$A$1:$A$1919,"<="&EOMONTH($A11,0)) | F11: =SUMIFS(Dados!$I$1:$I$1919,Dados!$K$1:$K$1919,Tp.Despesas!F$7,Dados!$A$1:$A$1919,">="&$A11,Dados!$A$1:$A$1919,"<="&EOMONTH($A11,0)) | G11: =SUMIFS(Dados!$I$1:$I$1919,Dados!$K$1:$K$1919,Tp.Despesas!G$7,Dados!$A$1:$A$1919,">="&$A11,Dados!$A$1:$A$1919,"<="&EOMONTH($A11,0)) | H11: =SUMIFS(Dados!$I$1:$I$1919,Dados!$K$1:$K$1919,Tp.Despesas!H$7,Dados!$A$1:$A$1919,">="&$A11,Dados!$A$1:$A$1919,"<="&EOMONTH($A11,0)) | I11: =SUMIFS(Dados!$I$1:$I$1919,Dados!$K$1:$K$1919,Tp.Despesas!I$7,Dados!$A$1:$A$1919,">="&$A11,Dados!$A$1:$A$1919,"<="&EOMONTH($A11,0)) | J11: =SUM(C11:I11)
A12: =EOMONTH(A11,1)-DAY(EOMONTH(A11,1))+1 | C12: =SUMIFS(Dados!$I$1:$I$1919,Dados!$K$1:$K$1919,Tp.Despesas!C$7,Dados!$A$1:$A$1919,">="&$A12,Dados!$A$1:$A$1919,"<="&EOMONTH($A12,0)) | D12: =SUMIFS(Dados!$I$1:$I$1919,Dados!$K$1:$K$1919,Tp.Despesas!D$7,Dados!$A$1:$A$1919,">="&$A12,Dados!$A$1:$A$1919,"<="&EOMONTH($A12,0)) | E12: =SUMIFS(Dados!$I$1:$I$1919,Dados!$K$1:$K$1919,Tp.Despesas!E$7,Dados!$A$1:$A$1919,">="&$A12,Dados!$A$1:$A$1919,"<="&EOMONTH($A12,0)) | F12: =SUMIFS(Dados!$I$1:$I$1919,Dados!$K$1:$K$1919,Tp.Despesas!F$7,Dados!$A$1:$A$1919,">="&$A12,Dados!$A$1:$A$1919,"<="&EOMONTH($A12,0)) | G12: =SUMIFS(Dados!$I$1:$I$1919,Dados!$K$1:$K$1919,Tp.Despesas!G$7,Dados!$A$1:$A$1919,">="&$A12,Dados!$A$1:$A$1919,"<="&EOMONTH($A12,0)) | H12: =SUMIFS(Dados!$I$1:$I$1919,Dados!$K$1:$K$1919,Tp.Despesas!H$7,Dados!$A$1:$A$1919,">="&$A12,Dados!$A$1:$A$1919,"<="&EOMONTH($A12,0)) | I12: =SUMIFS(Dados!$I$1:$I$1919,Dados!$K$1:$K$1919,Tp.Despesas!I$7,Dados!$A$1:$A$1919,">="&$A12,Dados!$A$1:$A$1919,"<="&EOMONTH($A12,0)) | J12: =SUM(C12:I12)
A13: =EOMONTH(A12,1)-DAY(EOMONTH(A12,1))+1 | C13: =SUMIFS(Dados!$I$1:$I$1919,Dados!$K$1:$K$1919,Tp.Despesas!C$7,Dados!$A$1:$A$1919,">="&$A13,Dados!$A$1:$A$1919,"<="&EOMONTH($A13,0)) | D13: =SUMIFS(Dados!$I$1:$I$1919,Dados!$K$1:$K$1919,Tp.Despesas!D$7,Dados!$A$1:$A$1919,">="&$A13,Dados!$A$1:$A$1919,"<="&EOMONTH($A13,0)) | E13: =SUMIFS(Dados!$I$1:$I$1919,Dados!$K$1:$K$1919,Tp.Despesas!E$7,Dados!$A$1:$A$1919,">="&$A13,Dados!$A$1:$A$1919,"<="&EOMONTH($A13,0)) | F13: =SUMIFS(Dados!$I$1:$I$1919,Dados!$K$1:$K$1919,Tp.Despesas!F$7,Dados!$A$1:$A$1919,">="&$A13,Dados!$A$1:$A$1919,"<="&EOMONTH($A13,0)) | G13: =SUMIFS(Dados!$I$1:$I$1919,Dados!$K$1:$K$1919,Tp.Despesas!G$7,Dados!$A$1:$A$1919,">="&$A13,Dados!$A$1:$A$1919,"<="&EOMONTH($A13,0)) | H13: =SUMIFS(Dados!$I$1:$I$1919,Dados!$K$1:$K$1919,Tp.Despesas!H$7,Dados!$A$1:$A$1919,">="&$A13,Dados!$A$1:$A$1919,"<="&EOMONTH($A13,0)) | I13: =SUMIFS(Dados!$I$1:$I$1919,Dados!$K$1:$K$1919,Tp.Despesas!I$7,Dados!$A$1:$A$1919,">="&$A13,Dados!$A$1:$A$1919,"<="&EOMONTH($A13,0)) | J13: =SUM(C13:I13)
A14: =EOMONTH(A13,1)-DAY(EOMONTH(A13,1))+1 | C14: =SUMIFS(Dados!$I$1:$I$1919,Dados!$K$1:$K$1919,Tp.Despesas!C$7,Dados!$A$1:$A$1919,">="&$A14,Dados!$A$1:$A$1919,"<="&EOMONTH($A14,0)) | D14: =SUMIFS(Dados!$I$1:$I$1919,Dados!$K$1:$K$1919,Tp.Despesas!D$7,Dados!$A$1:$A$1919,">="&$A14,Dados!$A$1:$A$1919,"<="&EOMONTH($A14,0)) | E14: =SUMIFS(Dados!$I$1:$I$1919,Dados!$K$1:$K$1919,Tp.Despesas!E$7,Dados!$A$1:$A$1919,">="&$A14,Dados!$A$1:$A$1919,"<="&EOMONTH($A14,0)) | F14: =SUMIFS(Dados!$I$1:$I$1919,Dados!$K$1:$K$1919,Tp.Despesas!F$7,Dados!$A$1:$A$1919,">="&$A14,Dados!$A$1:$A$1919,"<="&EOMONTH($A14,0)) | G14: =SUMIFS(Dados!$I$1:$I$1919,Dados!$K$1:$K$1919,Tp.Despesas!G$7,Dados!$A$1:$A$1919,">="&$A14,Dados!$A$1:$A$1919,"<="&EOMONTH($A14,0)) | H14: =SUMIFS(Dados!$I$1:$I$1919,Dados!$K$1:$K$1919,Tp.Despesas!H$7,Dados!$A$1:$A$1919,">="&$A14,Dados!$A$1:$A$1919,"<="&EOMONTH($A14,0)) | I14: =SUMIFS(Dados!$I$1:$I$1919,Dados!$K$1:$K$1919,Tp.Despesas!I$7,Dados!$A$1:$A$1919,">="&$A14,Dados!$A$1:$A$1919,"<="&EOMONTH($A14,0)) | J14: =SUM(C14:I14)
A15: =EOMONTH(A14,1)-DAY(EOMONTH(A14,1))+1 | C15: =SUMIFS(Dados!$I$1:$I$1919,Dados!$K$1:$K$1919,Tp.Despesas!C$7,Dados!$A$1:$A$1919,">="&$A15,Dados!$A$1:$A$1919,"<="&EOMONTH($A15,0)) | D15: =SUMIFS(Dados!$I$1:$I$1919,Dados!$K$1:$K$1919,Tp.Despesas!D$7,Dados!$A$1:$A$1919,">="&$A15,Dados!$A$1:$A$1919,"<="&EOMONTH($A15,0)) | E15: =SUMIFS(Dados!$I$1:$I$1919,Dados!$K$1:$K$1919,Tp.Despesas!E$7,Dados!$A$1:$A$1919,">="&$A15,Dados!$A$1:$A$1919,"<="&EOMONTH($A15,0)) | F15: =SUMIFS(Dados!$I$1:$I$1919,Dados!$K$1:$K$1919,Tp.Despesas!F$7,Dados!$A$1:$A$1919,">="&$A15,Dados!$A$1:$A$1919,"<="&EOMONTH($A15,0)) | G15: =SUMIFS(Dados!$I$1:$I$1919,Dados!$K$1:$K$1919,Tp.Despesas!G$7,Dados!$A$1:$A$1919,">="&$A15,Dados!$A$1:$A$1919,"<="&EOMONTH($A15,0)) | H15: =SUMIFS(Dados!$I$1:$I$1919,Dados!$K$1:$K$1919,Tp.Despesas!H$7,Dados!$A$1:$A$1919,">="&$A15,Dados!$A$1:$A$1919,"<="&EOMONTH($A15,0)) | I15: =SUMIFS(Dados!$I$1:$I$1919,Dados!$K$1:$K$1919,Tp.Despesas!I$7,Dados!$A$1:$A$1919,">="&$A15,Dados!$A$1:$A$1919,"<="&EOMONTH($A15,0)) | J15: =SUM(C15:I15)
A16: =EOMONTH(A15,1)-DAY(EOMONTH(A15,1))+1 | C16: =SUMIFS(Dados!$I$1:$I$1919,Dados!$K$1:$K$1919,Tp.Despesas!C$7,Dados!$A$1:$A$1919,">="&$A16,Dados!$A$1:$A$1919,"<="&EOMONTH($A16,0)) | D16: =SUMIFS(Dados!$I$1:$I$1919,Dados!$K$1:$K$1919,Tp.Despesas!D$7,Dados!$A$1:$A$1919,">="&$A16,Dados!$A$1:$A$1919,"<="&EOMONTH($A16,0)) | E16: =SUMIFS(Dados!$I$1:$I$1919,Dados!$K$1:$K$1919,Tp.Despesas!E$7,Dados!$A$1:$A$1919,">="&$A16,Dados!$A$1:$A$1919,"<="&EOMONTH($A16,0)) | F16: =SUMIFS(Dados!$I$1:$I$1919,Dados!$K$1:$K$1919,Tp.Despesas!F$7,Dados!$A$1:$A$1919,">="&$A16,Dados!$A$1:$A$1919,"<="&EOMONTH($A16,0)) | G16: =SUMIFS(Dados!$I$1:$I$1919,Dados!$K$1:$K$1919,Tp.Despesas!G$7,Dados!$A$1:$A$1919,">="&$A16,Dados!$A$1:$A$1919,"<="&EOMONTH($A16,0)) | H16: =SUMIFS(Dados!$I$1:$I$1919,Dados!$K$1:$K$1919,Tp.Despesas!H$7,Dados!$A$1:$A$1919,">="&$A16,Dados!$A$1:$A$1919,"<="&EOMONTH($A16,0)) | I16: =SUMIFS(Dados!$I$1:$I$1919,Dados!$K$1:$K$1919,Tp.Despesas!I$7,Dados!$A$1:$A$1919,">="&$A16,Dados!$A$1:$A$1919,"<="&EOMONTH($A16,0)) | J16: =SUM(C16:I16)
A17: =EOMONTH(A16,1)-DAY(EOMONTH(A16,1))+1 | C17: =SUMIFS(Dados!$I$1:$I$1919,Dados!$K$1:$K$1919,Tp.Despesas!C$7,Dados!$A$1:$A$1919,">="&$A17,Dados!$A$1:$A$1919,"<="&EOMONTH($A17,0)) | D17: =SUMIFS(Dados!$I$1:$I$1919,Dados!$K$1:$K$1919,Tp.Despesas!D$7,Dados!$A$1:$A$1919,">="&$A17,Dados!$A$1:$A$1919,"<="&EOMONTH($A17,0)) | E17: =SUMIFS(Dados!$I$1:$I$1919,Dados!$K$1:$K$1919,Tp.Despesas!E$7,Dados!$A$1:$A$1919,">="&$A17,Dados!$A$1:$A$1919,"<="&EOMONTH($A17,0)) | F17: =SUMIFS(Dados!$I$1:$I$1919,Dados!$K$1:$K$1919,Tp.Despesas!F$7,Dados!$A$1:$A$1919,">="&$A17,Dados!$A$1:$A$1919,"<="&EOMONTH($A17,0)) | G17: =SUMIFS(Dados!$I$1:$I$1919,Dados!$K$1:$K$1919,Tp.Despesas!G$7,Dados!$A$1:$A$1919,">="&$A17,Dados!$A$1:$A$1919,"<="&EOMONTH($A17,0)) | H17: =SUMIFS(Dados!$I$1:$I$1919,Dados!$K$1:$K$1919,Tp.Despesas!H$7,Dados!$A$1:$A$1919,">="&$A17,Dados!$A$1:$A$1919,"<="&EOMONTH($A17,0)) | I17: =SUMIFS(Dados!$I$1:$I$1919,Dados!$K$1:$K$1919,Tp.Despesas!I$7,Dados!$A$1:$A$1919,">="&$A17,Dados!$A$1:$A$1919,"<="&EOMONTH($A17,0)) | J17: =SUM(C17:I17)
A18: =EOMONTH(A17,1)-DAY(EOMONTH(A17,1))+1 | C18: =SUMIFS(Dados!$I$1:$I$1919,Dados!$K$1:$K$1919,Tp.Despesas!C$7,Dados!$A$1:$A$1919,">="&$A18,Dados!$A$1:$A$1919,"<="&EOMONTH($A18,0)) | D18: =SUMIFS(Dados!$I$1:$I$1919,Dados!$K$1:$K$1919,Tp.Despesas!D$7,Dados!$A$1:$A$1919,">="&$A18,Dados!$A$1:$A$1919,"<="&EOMONTH($A18,0)) | E18: =SUMIFS(Dados!$I$1:$I$1919,Dados!$K$1:$K$1919,Tp.Despesas!E$7,Dados!$A$1:$A$1919,">="&$A18,Dados!$A$1:$A$1919,"<="&EOMONTH($A18,0)) | F18: =SUMIFS(Dados!$I$1:$I$1919,Dados!$K$1:$K$1919,Tp.Despesas!F$7,Dados!$A$1:$A$1919,">="&$A18,Dados!$A$1:$A$1919,"<="&EOMONTH($A18,0)) | G18: =SUMIFS(Dados!$I$1:$I$1919,Dados!$K$1:$K$1919,Tp.Despesas!G$7,Dados!$A$1:$A$1919,">="&$A18,Dados!$A$1:$A$1919,"<="&EOMONTH($A18,0)) | H18: =SUMIFS(Dados!$I$1:$I$1919,Dados!$K$1:$K$1919,Tp.Despesas!H$7,Dados!$A$1:$A$1919,">="&$A18,Dados!$A$1:$A$1919,"<="&EOMONTH($A18,0)) | I18: =SUMIFS(Dados!$I$1:$I$1919,Dados!$K$1:$K$1919,Tp.Despesas!I$7,Dados!$A$1:$A$1919,">="&$A18,Dados!$A$1:$A$1919,"<="&EOMONTH($A18,0)) | J18: =SUM(C18:I18)
A19: =EOMONTH(A18,1)-DAY(EOMONTH(A18,1))+1 | C19: =SUMIFS(Dados!$I$1:$I$1919,Dados!$K$1:$K$1919,Tp.Despesas!C$7,Dados!$A$1:$A$1919,">="&$A19,Dados!$A$1:$A$1919,"<="&EOMONTH($A19,0)) | D19: =SUMIFS(Dados!$I$1:$I$1919,Dados!$K$1:$K$1919,Tp.Despesas!D$7,Dados!$A$1:$A$1919,">="&$A19,Dados!$A$1:$A$1919,"<="&EOMONTH($A19,0)) | E19: =SUMIFS(Dados!$I$1:$I$1919,Dados!$K$1:$K$1919,Tp.Despesas!E$7,Dados!$A$1:$A$1919,">="&$A19,Dados!$A$1:$A$1919,"<="&EOMONTH($A19,0)) | F19: =SUMIFS(Dados!$I$1:$I$1919,Dados!$K$1:$K$1919,Tp.Despesas!F$7,Dados!$A$1:$A$1919,">="&$A19,Dados!$A$1:$A$1919,"<="&EOMONTH($A19,0)) | G19: =SUMIFS(Dados!$I$1:$I$1919,Dados!$K$1:$K$1919,Tp.Despesas!G$7,Dados!$A$1:$A$1919,">="&$A19,Dados!$A$1:$A$1919,"<="&EOMONTH($A19,0)) | H19: =SUMIFS(Dados!$I$1:$I$1919,Dados!$K$1:$K$1919,Tp.Despesas!H$7,Dados!$A$1:$A$1919,">="&$A19,Dados!$A$1:$A$1919,"<="&EOMONTH($A19,0)) | I19: =SUMIFS(Dados!$I$1:$I$1919,Dados!$K$1:$K$1919,Tp.Despesas!I$7,Dados!$A$1:$A$1919,">="&$A19,Dados!$A$1:$A$1919,"<="&EOMONTH($A19,0)) | J19: =SUM(C19:I19)
A20: =EOMONTH(A19,1)-DAY(EOMONTH(A19,1))+1 | C20: =SUMIFS(Dados!$I$1:$I$1919,Dados!$K$1:$K$1919,Tp.Despesas!C$7,Dados!$A$1:$A$1919,">="&$A20,Dados!$A$1:$A$1919,"<="&EOMONTH($A20,0)) | D20: =SUMIFS(Dados!$I$1:$I$1919,Dados!$K$1:$K$1919,Tp.Despesas!D$7,Dados!$A$1:$A$1919,">="&$A20,Dados!$A$1:$A$1919,"<="&EOMONTH($A20,0)) | E20: =SUMIFS(Dados!$I$1:$I$1919,Dados!$K$1:$K$1919,Tp.Despesas!E$7,Dados!$A$1:$A$1919,">="&$A20,Dados!$A$1:$A$1919,"<="&EOMONTH($A20,0)) | F20: =SUMIFS(Dados!$I$1:$I$1919,Dados!$K$1:$K$1919,Tp.Despesas!F$7,Dados!$A$1:$A$1919,">="&$A20,Dados!$A$1:$A$1919,"<="&EOMONTH($A20,0)) | G20: =SUMIFS(Dados!$I$1:$I$1919,Dados!$K$1:$K$1919,Tp.Despesas!G$7,Dados!$A$1:$A$1919,">="&$A20,Dados!$A$1:$A$1919,"<="&EOMONTH($A20,0)) | H20: =SUMIFS(Dados!$I$1:$I$1919,Dados!$K$1:$K$1919,Tp.Despesas!H$7,Dados!$A$1:$A$1919,">="&$A20,Dados!$A$1:$A$1919,"<="&EOMONTH($A20,0)) | I20: =SUMIFS(Dados!$I$1:$I$1919,Dados!$K$1:$K$1919,Tp.Despesas!I$7,Dados!$A$1:$A$1919,">="&$A20,Dados!$A$1:$A$1919,"<="&EOMONTH($A20,0)) | J20: =SUM(C20:I20)
A21: =EOMONTH(A20,1)-DAY(EOMONTH(A20,1))+1 | C21: =SUMIFS(Dados!$I$1:$I$1919,Dados!$K$1:$K$1919,Tp.Despesas!C$7,Dados!$A$1:$A$1919,">="&$A21,Dados!$A$1:$A$1919,"<="&EOMONTH($A21,0)) | D21: =SUMIFS(Dados!$I$1:$I$1919,Dados!$K$1:$K$1919,Tp.Despesas!D$7,Dados!$A$1:$A$1919,">="&$A21,Dados!$A$1:$A$1919,"<="&EOMONTH($A21,0)) | E21: =SUMIFS(Dados!$I$1:$I$1919,Dados!$K$1:$K$1919,Tp.Despesas!E$7,Dados!$A$1:$A$1919,">="&$A21,Dados!$A$1:$A$1919,"<="&EOMONTH($A21,0)) | F21: =SUMIFS(Dados!$I$1:$I$1919,Dados!$K$1:$K$1919,Tp.Despesas!F$7,Dados!$A$1:$A$1919,">="&$A21,Dados!$A$1:$A$1919,"<="&EOMONTH($A21,0)) | G21: =SUMIFS(Dados!$I$1:$I$1919,Dados!$K$1:$K$1919,Tp.Despesas!G$7,Dados!$A$1:$A$1919,">="&$A21,Dados!$A$1:$A$1919,"<="&EOMONTH($A21,0)) | H21: =SUMIFS(Dados!$I$1:$I$1919,Dados!$K$1:$K$1919,Tp.Despesas!H$7,Dados!$A$1:$A$1919,">="&$A21,Dados!$A$1:$A$1919,"<="&EOMONTH($A21,0)) | I21: =SUMIFS(Dados!$I$1:$I$1919,Dados!$K$1:$K$1919,Tp.Despesas!I$7,Dados!$A$1:$A$1919,">="&$A21,Dados!$A$1:$A$1919,"<="&EOMONTH($A21,0)) | J21: =SUM(C21:I21)
... A44: =EOMONTH(A43,1)-DAY(EOMONTH(A43,1))+1 | C44: =SUMIFS(Dados!$I$1:$I$1919,Dados!$K$1:$K$1919,Tp.Despesas!C$7,Dados!$A$1:$A$1919,">="&$A44,Dados!$A$1:$A$1919,"<="&EOMONTH($A44,0)) | D44: =SUMIFS(Dados!$I$1:$I$1919,Dados!$K$1:$K$1919,Tp.Despesas!D$7,Dados!$A$1:$A$1919,">="&$A44,Dados!$A$1:$A$1919,"<="&EOMONTH($A44,0)) | E44: =SUMIFS(Dados!$I$1:$I$1919,Dados!$K$1:$K$1919,Tp.Despesas!E$7,Dados!$A$1:$A$1919,">="&$A44,Dados!$A$1:$A$1919,"<="&EOMONTH($A44,0)) | F44: =SUMIFS(Dados!$I$1:$I$1919,Dados!$K$1:$K$1919,Tp.Despesas!F$7,Dados!$A$1:$A$1919,">="&$A44,Dados!$A$1:$A$1919,"<="&EOMONTH($A44,0)) | G44: =SUMIFS(Dados!$I$1:$I$1919,Dados!$K$1:$K$1919,Tp.Despesas!G$7,Dados!$A$1:$A$1919,">="&$A44,Dados!$A$1:$A$1919,"<="&EOMONTH($A44,0)) | H44: =SUMIFS(Dados!$I$1:$I$1919,Dados!$K$1:$K$1919,Tp.Despesas!H$7,Dados!$A$1:$A$1919,">="&$A44,Dados!$A$1:$A$1919,"<="&EOMONTH($A44,0)) | I44: =SUMIFS(Dados!$I$1:$I$1919,Dados!$K$1:$K$1919,Tp.Despesas!I$7,Dados!$A$1:$A$1919,">="&$A44,Dados!$A$1:$A$1919,"<="&EOMONTH($A44,0)) | J44: =SUM(C44:I44)
A45: TOTAL GERAL | C45: =SUM(C9:C44) | D45: =SUM(D9:D44) | E45: =SUM(E9:E44) | F45: =SUM(F9:F44) | G45: =SUM(G9:G44) | H45: =SUM(H9:H44) | I45: =SUM(I9:I44) | J45: =SUM(J9:J44)
C46: =C45/$J$45 | D46: =D45/$J$45 | E46: =E45/$J$45 | F46: =F45/$J$45 | G46: =G45/$J$45 | H46: =H45/$J$45 | I46: =I45/$J$45 | J46: =J45/$J$45
J48: =RESUMO!L80
J49: =J48-J45

Sheet Contratos_ADM
A1: CONTRATOS | G1: ADMINISTRADORES_CONTRATO | N1: ADITIVOS | R1: ADMINISTRADORES_ADITIVO | Y1: PARCELAS
A2: Nº Contrato | B2: Data Início | C2: Data Fim | D2: Status | E2: Observações | G2: Nº Contrato | H2: CNPJ/CPF | I2: Nome/Razão Social | J2: Tipo | K2: Valor/Percentual | L2: Valor Total | M2: Nº Parcelas | N2: Nº Contrato | O2: Nº Aditivo | P2: Data Início | Q2: Data Fim | R2: Nº Contrato | S2: Nº Aditivo | T2: CNPJ/CPF | U2: Nome/Razão Social | V2: Tipo | W2: Valor/Percentual | X2: Valor Total | Y2: Referência | Z2: Número | AA2: CNPJ/CPF | AB2: Data Vencimento | AC2: Valor | AD2: Status
A3: 2024/010 | B3: 45540 | C3: 46635 | D3: ATIVO
G4: 2024/010 | H4: 30104762000107 | I4: VASCONCELOS & RINALDI ENGENHARIA | J4: Percentual | K4: 13
